Workbook

Sheet VC shortlist
A2: India semiconductor startup investment screen
A3: As of 1 October 2026. Five diligence candidates; valuation, fund mandate and allocation availability remain unverified.
A5: Company | B5: Investment stance | C5: Why it merits diligence | D5: Buyer evidence | E5: Conditions before investment | F5: Stage / financing approach | G5: Exit route and constraint | I5: Candidate | J5: Disclosed funding (USD Mn)
A6: Vervesemi Microelectronics | B6: Prioritise commercialisation diligence | C6: Experienced analog team, fabricated product samples and several industrial use cases offer a credible route to long-lived design wins. | D6: Customer evaluation reported, but public names and committed volumes remain limited. | E6: Validate qualified SKUs, yields, gross margin after packaging/test, and two independent paying OEM design wins. | F6: Series A participation or follow-on after production qualification; avoid pricing IP-count as revenue. | G6: Product/IP sale to an analog incumbent or profitable scale-up. No exit value assumed. | I6: Vervesemi Microelectronics | J6: =Funding!C7 -> 10
A7: InCore Semiconductors | B7: Prioritise IP commercial diligence | C7: Reusable processor IP and design automation can create licensing revenue with less wafer inventory exposure than a chip-product business. | D7: Named HCL/Tessolve collaborations and partner-silicon evidence. Licence economics undisclosed. | E7: Confirm clean IP ownership, paid licences, customer tape-outs, royalty audit rights and support burden. | F7: Seed/Series A growth after paid design wins; reserve capital for engineering and international sales. | G7: Processor/IP acquisition or strategic licensing-led growth. RISC-V competition may compress prices. | I7: InCore Semiconductors | J7: =Funding!C9 -> 3
A8: FermionIC Design | B8: Prioritise customer qualification diligence | C8: Focused RF products, prototype evidence, a global foundry route and distribution channel support a differentiated niche. | D8: GF manufacturing agreement and DigiKey channel are verified relationships, not end-customer orders. | E8: Obtain customer references, signed qualification milestones, RF reliability results and volume-priced wafer/package quotes. | F8: Early growth round tied to customer qualification and first repeat shipments. | G8: Strategic acquisition by an RF/analog supplier; defence concentration may constrain growth. | I8: FermionIC Design | J8: =Funding!C8 -> 6
A9: Mindgrove Technologies | B9: Prioritise first-revenue conversion | C9: Working SecureIoT silicon, local application support and specific Indian device use cases reduce initial engineering uncertainty. | D9: Bosch/Pinetics relationships and trials are encouraging; recurring order book remains unverified. | E9: Confirm paid orders, field failure rates, firmware support cost, delivered unit margin and customer switching economics. | F9: Series A follow-on tied to first repeat commercial orders; retain funding for next chip revision. | G9: Strategic chip/OEM acquisition or a broader industrial-controller portfolio. Commodity MCU competition is a risk. | I9: Mindgrove Technologies | J9: =Funding!C6 -> 10.32
A10: Maieutic Semiconductors | B10: Prioritise paid software pilots | C10: Repeat semiconductor founders and reusable design software create a potentially efficient way to monetise scarce analog expertise. | D10: No named paying customer verified; investor quality and prior founder exit cannot substitute for software adoption. | E10: Require paid pilots, reproducible design-time savings, data-security approval and compatibility with standard EDA flows. | F10: Seed/Series A only after pilot evidence; build licence and renewal economics before scaling sales. | G10: EDA/engineering-software acquisition or independent licence growth. Incumbent bundling is the main strategic risk. | I10: Maieutic Semiconductors | J10: =Funding!C10 -> 6
A13: Exclusions and watchlist
A14: C2i | B14: Infineon acquisition announced August 2026. Treat as an exit precedent, not an available independent startup.
A15: Agnit | B15: Strong GaN research; manufacturing yield, capital intensity and pilot conversion justify a separate high-risk track.
A16: Netrasemi / BigEndian | B16: Track software maturity, camera/OEM qualification and repeat orders. Funding and tape-out alone do not establish a commercial moat.
A17: Meukron / SimYog | B17: Watch manufacturing tools and design software: capital efficiency can be attractive, but repeat sales/renewals need verification.
A18: Large fabs / OSAT projects | B18: Project capex and subsidy approvals are not VC funding. Corporate ventures and listed companies have different investment structures.
A74: Servers, data centres & storage | B74: 361 | C74: =B74/$B$81 -> 0.34315589
A75: Smartphones | B75: 192 | C75: =B75/$B$81 -> 0.18250951
A76: Industrial electronics | B76: 120 | C76: =B76/$B$81 -> 0.11406844
A77: Automotive | B77: 114 | C77: =B77/$B$81 -> 0.10836502
A78: Personal computing | B78: 112 | C78: =B78/$B$81 -> 0.10646388
A79: Consumer electronics | B79: 83 | C79: =B79/$B$81 -> 0.078897338
A80: Wired & wireless communication | B80: 70 | C80: =B80/$B$81 -> 0.066539924
B81: =SUM(B74:B80) -> 1052 | C81: =SUM(C74:C80) -> 1

Sheet Company universe
A2: Company universe and scope
A3: 120 entries: 54 company-specific profiles, the complete 103-entry April 2026 EDA roster, plus boundary/discovery entries. This is not a certified census.
A5: ID | B5: Company | C5: Product / service category | D5: Ownership / eligibility boundary | E5: State / India link | F5: Research coverage | G5: Official EDA roster no. | H5: Source IDs
A6: IN001 | B6: Mindgrove Technologies | C6: Embedded processors and edge AI | D6: Independent private company | E6: Tamil Nadu | F6: Company-specific research | G6: 54 | H6: S002, S003, S004, S005, S006, S001
A7: IN002 | B7: Vervesemi Microelectronics | C7: Analog, mixed-signal and power | D7: Independent private company | E7: Uttar Pradesh | F7: Company-specific research | G7: 91 | H7: S007, S008, S009, S010, S001
A8: IN003 | B8: FermionIC Design | C8: RF, radar and wireless chips | D8: Independent private company | E8: Karnataka | F8: Company-specific research | G8: 1 | H8: S011, S012, S013, S014, S015, S016, S001
A9: IN004 | B9: InCore Semiconductors | C9: Processor and interface IP | D9: Independent private company | E9: Tamil Nadu | F9: Company-specific research | G9: 52 | H9: S017, S018, S019, S020, S021, S001
A10: IN005 | B10: Maieutic Semiconductors | C10: Design software and EDA | D10: Independent private company | E10: Karnataka | F10: Company-specific research | G10: 41 | H10: S022, S023, S024, S025, S001
A11: IN006 | B11: C2i Semiconductors | C11: Analog, mixed-signal and power | D11: Acquisition announced; exclude from fresh VC shortlist | E11: Karnataka | F11: Company-specific research | G11: 21 | H11: S026, S027, S028, S029, S001
A12: IN007 | B12: Agnit Semiconductors | C12: Compound semiconductors and materials | D12: Independent private company | E12: Karnataka | F12: Company-specific research | H12: S030, S031, S032, S033
A13: IN008 | B13: Netrasemi | C13: Embedded processors and edge AI | D13: Independent private company | E13: Kerala | F13: Company-specific research | G13: 59 | H13: S034, S035, S036, S037, S038, S001
A14: IN009 | B14: BigEndian Semiconductors | C14: Embedded processors and edge AI | D14: Independent private company | E14: Karnataka | F14: Company-specific research | G14: 6 | H14: S039, S040, S041, S001
A15: IN010 | B15: Morphing Machines | C15: Compute accelerators | D15: Independent private company | E15: Karnataka | F15: Company-specific research | G15: 2 | H15: S042, S043, S044, S045, S001
A16: IN011 | B16: Calligo Technologies | C16: Compute accelerators | D16: Independent private company | E16: Karnataka | F16: Company-specific research | G16: 3 | H16: S046, S047, S048, S049, S050, S001
A17: IN012 | B17: HrdWyr | C17: Embedded processors and edge AI | D17: Independent private company | E17: Karnataka | F17: Company-specific research | H17: S051, S052, S053
A18: IN013 | B18: Agrani Labs | C18: Compute accelerators | D18: Independent private company | E18: Karnataka | F18: Company-specific research | H18: S054, S055
A19: IN014 | B19: Sensesemi Technologies | C19: Analog, mixed-signal and power | D19: Independent private company | E19: Karnataka | F19: Company-specific research | G19: 4 | H19: S056, S057, S001
A20: IN015 | B20: Aheesa Digital Innovations | C20: RF, radar and wireless chips | D20: Independent private company | E20: Tamil Nadu | F20: Company-specific research | G20: 51 | H20: S058, S059, S060, S061, S001
A21: IN016 | B21: Green PMU Semi | C21: Analog, mixed-signal and power | D21: Independent private company | E21: Telangana | F21: Company-specific research | G21: 63 | H21: S062, S063, S001
A22: IN017 | B22: MOSart Semi | C22: Analog, mixed-signal and power | D22: Independent private company | E22: Karnataka | F22: Company-specific research | H22: S064, S065
A23: IN018 | B23: DV2JS Innovation / 3rdiTech | C23: Sensors and MEMS | D23: Independent private company | E23: Delhi | F23: Company-specific research | G23: 97 | H23: S066, S067, S068, S001
A24: IN019 | B24: Aryabhata Circuits and Research Labs | C24: Sensors and MEMS | D24: Independent private company | E24: Karnataka | F24: Company-specific research | G24: 13 | H24: S069, S070, S001
A25: IN020 | B25: Silizium Circuits | C25: RF, radar and wireless chips | D25: Independent private company | E25: Kerala | F25: Company-specific research | G25: 60 | H25: S071, S072, S073, S001
A26: IN021 | B26: Sophrosyne Technologies | C26: Sensors and MEMS | D26: Independent private company | E26: Karnataka | F26: Company-specific research | G26: 19 | H26: S074, S075, S001
A27: IN022 | B27: MMRFIC Technology | C27: RF, radar and wireless chips | D27: Independent private company | E27: Karnataka | F27: Company-specific research | G27: 37 | H27: S076, S077, S078, S001
A28: IN023 | B28: MBit Wireless | C28: RF, radar and wireless chips | D28: Mature private company; India/overseas entity boundary needs diligence | E28: Tamil Nadu | F28: Company-specific research | G28: 58 | H28: S079, S080, S001
A29: IN024 | B29: Multi Nano Sense Technologies | C29: Sensors and MEMS | D29: Independent private company | E29: Maharashtra | F29: Company-specific research | G29: 83 | H29: S081, S082, S083, S084, S001
A30: IN025 | B30: Incise Infotech | C30: Chip-design services | D30: Established private services company | E30: Uttar Pradesh | F30: Company-specific research | G30: 92 | H30: S085, S086, S087, S001
A31: IN026 | B31: WiSig Networks | C31: RF, radar and wireless chips | D31: Independent private company | E31: Telangana | F31: Company-specific research | G31: 64 | H31: S088, S089, S090, S091, S001
A32: IN027 | B32: Aagyavision | C32: RF, radar and wireless chips | D32: Independent private company | E32: Karnataka | F32: Company-specific research | G32: 16 | H32: S092, S093, S094, S001
A33: IN028 | B33: Chipspirit Technologies | C33: Chip-design services | D33: Independent private company | E33: Karnataka | F33: Company-specific research | G33: 14 | H33: S095, S096, S097, S098, S001
A34: IN029 | B34: SandLogic Technologies | C34: Embedded processors and edge AI | D34: Independent private company | E34: Karnataka | F34: Company-specific research | G34: 12 | H34: S099, S100, S101, S102, S001
A35: IN030 | B35: SimYog Technology | C35: Design software and EDA | D35: Independent private company | E35: Karnataka | F35: Company-specific research | H35: S103, S104, S105, S106
A36: IN031 | B36: Ananant Systems | C36: RF, radar and wireless chips | D36: Independent private company | E36: Karnataka | F36: Company-specific research | G36: 40 | H36: S107, S108, S109, S001
A37: IN032 | B37: VASBEAM | C37: RF, radar and wireless chips | D37: Independent private company | E37: Maharashtra | F37: Company-specific research | G37: 79 | H37: S110, S111, S112, S001
A38: IN033 | B38: optoML | C38: Compute accelerators | D38: India-linked; Singapore parent / Indian operating entity | E38: Karnataka | F38: Company-specific research | G38: 44 | H38: S113, S114, S115, S116, S117, S001
A39: IN034 | B39: CIMware Technologies | C39: Compute systems and adjacent hardware | D39: Independent private company | E39: Karnataka | F39: Company-specific research | G39: 24 | H39: S118, S119, S001
A40: IN035 | B40: Nanojoules Semiconductors | C40: Embedded processors and edge AI | D40: Independent private company | E40: Karnataka | F40: Company-specific research | G40: 23 | H40: S120, S001
A41: IN036 | B41: Terminus Circuits | C41: Processor and interface IP | D41: Mature independent private company | E41: Karnataka | F41: Company-specific research | G41: 17 | H41: S121, S122, S001
A42: IN037 | B42: MemSmart | C42: Compute systems and adjacent hardware | D42: Independent private company | E42: Karnataka | F42: Company-specific research | G42: 9 | H42: S123, S001
A43: IN038 | B43: Quanfluence | C43: Photonics and quantum-adjacent hardware | D43: Independent private company | E43: Karnataka | F43: Company-specific research | G43: 11 | H43: S124, S125, S126, S001
A44: IN039 | B44: TriSpace Technologies | C44: Chip-design services | D44: Independent private company | E44: Karnataka | F44: Company-specific research | G44: 8 | H44: S127, S128, S001
A45: IN040 | B45: LineSemi Technology | C45: Analog, mixed-signal and power | D45: Independent private company | E45: Karnataka | F45: Company-specific research | G45: 22 | H45: S129, S130, S001
A46: IN041 | B46: Blueberry Semiconductors | C46: Chip-design services | D46: Independent private company | E46: Karnataka | F46: Company-specific research | H46: S131, S132, S133
A47: IN042 | B47: SignOff Semiconductors | C47: Chip-design services | D47: Independent private company | E47: Karnataka | F47: Company-specific research | H47: S134, S135, S136
A48: IN043 | B48: Signalchip Innovations | C48: RF, radar and wireless chips | D48: Mature independent private company | E48: Karnataka | F48: Company-specific research | G48: 31 | H48: S137, S138, S139, S140, S001
A49: IN044 | B49: Suchi Semicon | C49: Packaging, assembly and testing | D49: Promoter-backed private manufacturing venture | E49: Gujarat | F49: Company-specific research | H49: S141, S142, S143, S144
A50: IN045 | B50: RRP Electronics | C50: Packaging, assembly and testing | D50: Promoter-backed private manufacturing venture; distinguish from listed RRP entities | E50: Maharashtra | F50: Company-specific research | H50: S145, S146, S147
A51: IN046 | B51: Ceremorphic | C51: Compute accelerators | D51: India-linked; US-headquartered with Indian R&D | E51: Telangana / US headquarters | F51: Company-specific research | H51: S148, S149, S150
A52: IN047 | B52: Tattvam AI | C52: Design software and EDA | D52: India-origin; overseas headquarters, outside India-core startup count | E52: London / India-origin founder | F52: Company-specific research | H52: S151
A53: IN048 | B53: Aura Semiconductor | C53: Analog, mixed-signal and power | D53: Mature India-origin multinational; ownership/product perimeter needs review | E53: Karnataka | F53: Company-specific research | H53: S152, S153, S154
A54: IN049 | B54: SiCSem | C54: Compound semiconductors and materials | D54: Archean Chemical Industries-backed corporate venture | E54: Odisha | F54: Company-specific research | H54: S155, S156, S157
A55: IN050 | B55: Saankhya Labs | C55: RF, radar and wireless chips | D55: Acquired / Tejas Networks group; not independent VC candidate | E55: Karnataka | F55: Company-specific research | G55: 5 | H55: S158, S159, S001
A56: IN051 | B56: Meukron Technologies | C56: Manufacturing equipment and process tools | D56: Independent private company | E56: Karnataka | F56: Company-specific research | H56: S160, S161, S162
A57: IN052 | B57: LeadSOC Technologies | C57: Chip-design services | D57: Independent private company | E57: Karnataka | F57: Company-specific research | G57: 35 | H57: S163, S164, S001
A58: IN053 | B58: BITSILICA | C58: Chip-design services | D58: Acquired by Quest Global; not independent VC candidate | E58: Telangana | F58: Company-specific research | G58: 67 | H58: S165, S166, S001
A59: IN054 | B59: IndieSemiC | C59: RF, radar and wireless chips | D59: Independent private company | E59: Gujarat | F59: Company-specific research | G59: 85 | H59: S167, S168, S169, S170, S171, S001
A60: IN055 | B60: Stteereng Silicon | C60: Chip design — product category unverified | D60: Programme-listed entity; startup independence unverified | E60: Karnataka | F60: Roster only — company-level diligence outstanding | G60: 7 | H60: S001
A61: IN056 | B61: Silicon Support Solution (OPC) | C61: Chip design — product category unverified | D61: Programme-listed entity; startup independence unverified | E61: Karnataka | F61: Roster only — company-level diligence outstanding | G61: 10 | H61: S001
A62: IN057 | B62: Tsilicon | C62: Chip design — product category unverified | D62: Programme-listed entity; startup independence unverified | E62: Karnataka | F62: Roster only — company-level diligence outstanding | G62: 15 | H62: S001
A63: IN058 | B63: Semiksha Semiconductors | C63: Chip design — product category unverified | D63: Programme-listed entity; startup independence unverified | E63: Karnataka | F63: Roster only — company-level diligence outstanding | G63: 18 | H63: S001
A64: IN059 | B64: iSOC Semiconductors | C64: Chip design — product category unverified | D64: Programme-listed entity; startup independence unverified | E64: Karnataka | F64: Roster only — company-level diligence outstanding | G64: 20 | H64: S001
A65: IN060 | B65: PrimeSOC Technologies LLP | C65: Chip design — product category unverified | D65: Programme-listed entity; startup independence unverified | E65: Karnataka | F65: Roster only — company-level diligence outstanding | G65: 25 | H65: S001
A66: IN061 | B66: Ciliconchip Circuit | C66: Chip design — product category unverified | D66: Programme-listed entity; startup independence unverified | E66: Karnataka | F66: Roster only — company-level diligence outstanding | G66: 26 | H66: S001
A67: IN062 | B67: Memrym Solutions India | C67: Chip design — product category unverified | D67: Programme-listed entity; startup independence unverified | E67: Karnataka | F67: Roster only — company-level diligence outstanding | G67: 27 | H67: S001
A68: IN063 | B68: MAXVY Technologies | C68: Chip design — product category unverified | D68: Programme-listed entity; startup independence unverified | E68: Karnataka | F68: Roster only — company-level diligence outstanding | G68: 28 | H68: S001
... A122: IN117 | B122: Aantaric Technologies | C122: Chip design — product category unverified | D122: Programme-listed entity; startup independence unverified | E122: West Bengal | F122: Roster only — company-level diligence outstanding | G122: 103 | H122: S001
A123: IN118 | B123: MosChip Technologies | C123: Chip-design services | D123: Listed incumbent; not a startup investment candidate | E123: Telangana | F123: Programme / incumbent context | H123: S172, S001
A124: IN119 | B124: Elphins Technologies | C124: Photonics — detailed product unverified | D124: Emerging private venture; ownership verification pending | E124: India | F124: Event lead — company-level diligence outstanding | H124: S173
A125: IN120 | B125: CraftifAI Technologies | C125: Design software — detailed product unverified | D125: Emerging private venture; ownership verification pending | E125: India | F125: Event lead — company-level diligence outstanding | H125: S174

Sheet Funding
A2: Funding totals and reconciliation
A3: Blank numeric cells mean unavailable, never zero. Totals have different disclosure completeness; do not sum the column as sector funding.
A5: ID | B5: Company | C5: Reported / reconstructed total (USD Mn) | D5: Disclosed rounds / events | E5: Last financing date | F5: Date precision | G5: Investors / financing source | H5: Basis, discrepancy and completeness | I5: Source IDs
A6: IN001 | B6: Mindgrove Technologies | C6: =SUMIF('Funding events'!$A$6:$A$37,B6,'Funding events'!$D$6:$D$37) -> 10.32 | D6: 2 | E6: 2024-12 | F6: Month | G6: Peak XV, Speciale, Whiteboard; Mela and other Series A investors | H6: USD 2.32 Mn seed + USD 8 Mn Series A; disclosed equity only. | I6: S002, S003, S004, S005, S006, S001
A7: IN002 | B7: Vervesemi Microelectronics | C7: =SUMIF('Funding events'!$A$6:$A$37,B7,'Funding events'!$D$6:$D$37) -> 10 | D7: 1 | E7: 46071 | F7: Day | G7: Ashish Kacholia, Unicorn India Ventures, Roots Ventures, Caperize, MAIQ | H7: USD 10 Mn Series A is the publicly quantified round. Earlier private capital, if any, is not reconciled. | I7: S007, S008, S009, S010, S001
A8: IN003 | B8: FermionIC Design | C8: =SUMIF('Funding events'!$A$6:$A$37,B8,'Funding events'!$D$6:$D$37) -> 6 | D8: 1 | E8: 2024 | F8: Year | G8: Ashish Kacholia and associates | H8: USD 6 Mn disclosed round; sources disagree on month (September versus December 2024), so year precision is retained. | I8: S011, S012, S013, S014, S015, S016, S001
A9: IN004 | B9: InCore Semiconductors | C9: =SUMIF('Funding events'!$A$6:$A$37,B9,'Funding events'!$D$6:$D$37) -> 3 | D9: 1 | E9: 2023-05 | F9: Month | G9: Peak XV / then Sequoia Capital India | H9: USD 3 Mn seed, rounded from database USD 2.99 Mn. No later closed round verified. | I9: S017, S018, S019, S020, S021, S001
A10: IN005 | B10: Maieutic Semiconductors | C10: =SUMIF('Funding events'!$A$6:$A$37,B10,'Funding events'!$D$6:$D$37) -> 6 | D10: 1 | E10: 45951 | F10: Day | G10: Endiya Partners, Exfinity Venture Partners, UTEC | H10: One seed round expanded from USD 4.15 Mn to USD 6 Mn. Do not add the two announcements. Last date is public expanded-round announcement. | I10: S022, S023, S024, S025, S001
A11: IN006 | B11: C2i Semiconductors | C11: =SUMIF('Funding events'!$A$6:$A$37,B11,'Funding events'!$D$6:$D$37) -> 20.7 | D11: 2 | E11: 46169 | F11: Day | G11: Yali, Lip-Bu Tan, Peak XV, TDK Ventures | H11: USD 4 Mn seed plus USD 16.7 Mn expanded Series A. February USD 15 Mn was part of the same A. Acquisition price undisclosed and excluded. | I11: S026, S027, S028, S029, S001
A12: IN007 | B12: Agnit Semiconductors | C12: =SUMIF('Funding events'!$A$6:$A$37,B12,'Funding events'!$D$6:$D$37) -> 7.4 | D12: 3 | E12: 2026-03 | F12: Month | G12: Lakshmi Narayanan / angels; 3one4, Zephyr Peacock, Shastra VC | H12: Provisional disclosed-event sum: USD 1.3 Mn angel (2021) + 3.5 Mn seed (2024) + 2.6 Mn extension (2026). Some databases show only USD 6.1 Mn/2 events; older total USD 4.87 Mn also differs. Confirm cap table; do not average different scopes. | I12: S030, S031, S032, S033
A13: IN008 | B13: Netrasemi | C13: 14.6 | D13: 3 | E13: 45862 | F13: Day | G13: Unicorn India Ventures, Zoho and earlier investors | H13: Tracxn FY25–26 reports USD 14.6 Mn. Disclosed INR events: 8.3 crore seed + 10 crore pre-A + 107 crore A = 125.3 crore. Inc42 USD 13.6 Mn/2 rounds appears to omit an earlier round. No averaging across scopes. | I13: S034, S035, S036, S037, S038, S001
A14: IN009 | B14: BigEndian Semiconductors | C14: =SUMIF('Funding events'!$A$6:$A$37,B14,'Funding events'!$D$6:$D$37) -> 9 | D14: 2 | E14: 46148 | F14: Day | G14: Vertex Ventures, IAN Alpha, IvyCap and others | H14: USD 3 Mn seed (2024) plus USD 6 Mn pre-Series A (2026). | I14: S039, S040, S041, S001
A15: IN010 | B15: Morphing Machines | C15: 14.22 | D15: 4 | E15: 46139 | F15: Day | G15: Speciale and other disclosed syndicate investors; validate full cap table | H15: Inc42 database total and event count. Latest INR 42 crore extension took Series A to INR 80 crore; do not add INR 80 crore on top of the extension. Underlying 4-event ledger not fully public. | I15: S042, S043, S044, S045, S001
A16: IN011 | B16: Calligo Technologies | C16: 2.67 | D16: 3 | E16: 45754 | F16: Day | G16: Seafund, Artha, Karnataka semiconductor fund and others | H16: Caplight total USD 2.67 Mn and Crunchbase 3 events; only USD 1.1 Mn April 2025 pre-A is directly quantified in recent reporting. Inc42 shows USD 1.1 Mn/2 events. Proposed USD 12–15 Mn 2026 raise excluded. | I16: S046, S047, S048, S049, S050, S001
A17: IN012 | B17: HrdWyr | C17: 13 | D17: 1 | E17: 46154 | F17: Day | G17: Ideaspring, Singularity, Avatar, Persistent Systems | H17: USD 13 Mn Series A; 1 quantified publicly disclosed financing event, not proof of no earlier capital. | I17: S051, S052, S053
A18: IN013 | B18: Agrani Labs | C18: 8 | D18: 1 | E18: 46050 | F18: Day | G18: Peak XV and angels | H18: USD 8 Mn seed announced January 2026. Database USD 15.3 Mn/2 events may overlap earlier closing; not added without reconciliation. Reported USD 50 Mn discussions excluded. | I18: S054, S055
A19: IN014 | B19: Sensesemi Technologies | C19: 2.7 | D19: 1 | E19: 46044 | F19: Day | G19: Piper Serica and angel/investor syndicate | H19: INR 25 crore seed, reported approximately USD 2.7 Mn; announcement-day difference across databases. | I19: S056, S057, S001
A20: IN015 | B20: Aheesa Digital Innovations | E20: 2026 | F20: Year | G20: TNIFMC / TNESSF and private investors | H20: PIB reports about INR 40 crore raised across successive rounds during 2026. TNIFMC announced INR 20 crore in March. Full round count and latest closing date remain unverified; public-fund equity is not subsidy. | I20: S058, S059, S060, S061, S001
A21: IN016 | B21: Green PMU Semi | F21: Unverified | G21: Not publicly verified | H21: No reliable company-specific total, round count or last financing date found in reviewed sources. | I21: S062, S063, S001
A22: IN017 | B22: MOSart Semi | F22: Unverified | G22: Not publicly verified | H22: No reliable company-specific total, round count or last financing date found in reviewed sources. | I22: S064, S065
A23: IN018 | B23: DV2JS Innovation / 3rdiTech | C23: 0.11 | D23: 1 | E23: 44061 | F23: Day | G23: Berkeley SkyDeck; other strategic investors undisclosed | H23: CB Insights records USD 0.11 Mn convertible note. This is a known historical event, not a complete lifetime funding total; later strategic investors reported without amounts. | I23: S066, S067, S068, S001
A24: IN019 | B24: Aryabhata Circuits and Research Labs | F24: Unverified | G24: Not publicly verified | H24: No reliable company-specific total, round count or last financing date found in reviewed sources. | I24: S069, S070, S001
A25: IN020 | B25: Silizium Circuits | F25: Unverified | G25: Not publicly verified | H25: No reliable company-specific total, round count or last financing date found in reviewed sources. | I25: S071, S072, S073, S001
A26: IN021 | B26: Sophrosyne Technologies | C26: 2 | D26: 1 | E26: 45982 | F26: Day | G26: Bluehill VC | H26: USD 2 Mn seed; database header shows 20 November while announcement/FAQ shows 21 November. | I26: S074, S075, S001
A27: IN022 | B27: MMRFIC Technology | F27: Unverified | G27: Sansera Engineering; earlier investors require reconciliation | H27: Sansera INR 20 crore investment for 22% reported in 2023-era disclosures. Lifetime equity total and complete round count not verified. | I27: S076, S077, S078, S001
A28: IN023 | B28: MBit Wireless | F28: Unverified | G28: Not publicly verified | H28: No reliable company-specific total, round count or last financing date found in reviewed sources. | I28: S079, S080, S001
A29: IN024 | B29: Multi Nano Sense Technologies | F29: Unverified | G29: Public development finance separately recorded | H29: Equity funding not reconciled. CB Insights labels historical USD 0.41 Mn as grant, while company/TDB sources indicate soft-loan support; excluded from equity. | I29: S081, S082, S083, S084, S001
A30: IN025 | B30: Incise Infotech | F30: Unverified | G30: Not publicly verified | H30: No reliable company-specific total, round count or last financing date found in reviewed sources. | I30: S085, S086, S087, S001
A31: IN026 | B31: WiSig Networks | C31: 1 | F31: Unverified | G31: Funding composition requires confirmation | H31: Bharat Innovates 2026 profile reports USD 1 Mn funding; equity-versus-grant split, round count and latest financing date not disclosed. | I31: S088, S089, S090, S091, S001
A32: IN027 | B32: Aagyavision | F32: Unverified | G32: Not publicly verified | H32: No reliable company-specific total, round count or last financing date found in reviewed sources. | I32: S092, S093, S094, S001
A33: IN028 | B33: Chipspirit Technologies | D33: 1 | E33: 2021 | F33: Year | G33: SFAL / incubator support; instrument classification to confirm | H33: Crunchbase records one financing round; amount undisclosed. CB Insights gives January 2021 but precise date is not independently confirmed. | I33: S095, S096, S097, S098, S001
A34: IN029 | B34: SandLogic Technologies | C34: 4 | E34: 2022-02 | F34: Month | G34: Texas-based HNIs; full investor/instrument ledger to verify | H34: USD 4 Mn historical funding reported. Crunchbase counts 3 events but full instrument ledger is inaccessible. USD 30–40 Mn 2025 financing discussions are not a closed round. | I34: S099, S100, S101, S102, S001
A35: IN030 | B35: SimYog Technology | D35: 3 | E35: 45274 | F35: Day | G35: Mela Ventures, 1Crowd, Ideaspring, Bosch | H35: Crunchbase reports 3 rounds. INR 20 crore Series A (about USD 2.4 Mn) in December 2023 and INR 6.3 crore earlier round reported. Complete total not reconciled. | I35: S103, S104, S105, S106
A36: IN031 | B36: Ananant Systems | C36: 3 | F36: Unverified | G36: SIIC ecosystem and undisclosed investors | H36: Bharat Innovates 2026 profile reports approximately USD 3 Mn. Complete round dates/count undisclosed. September USD 5 Mn proposed government/RDI raise excluded. | I36: S107, S108, S109, S001
A37: IN032 | B37: VASBEAM | F37: Unverified | G37: Not publicly verified | H37: No reliable company-specific total, round count or last financing date found in reviewed sources. | I37: S110, S111, S112, S001
A38: IN033 | B38: optoML | C38: 1.8 | D38: 1 | E38: 46077 | F38: Day | G38: Bluehill VC, A99 | H38: USD 1.8 Mn pre-Series A/seed (stage terminology differs by source). | I38: S113, S114, S115, S116, S117, S001
A39: IN034 | B39: CIMware Technologies | C39: 2.3 | D39: 1 | E39: 45840 | F39: Day | G39: Transition VC | H39: USD 2.3 Mn pre-Series A / first disclosed equity round. | I39: S118, S119, S001
A40: IN035 | B40: Nanojoules Semiconductors | F40: Unverified | G40: Not publicly verified | H40: No reliable company-specific total, round count or last financing date found in reviewed sources. | I40: S120, S001
A41: IN036 | B41: Terminus Circuits | F41: Unverified | G41: Not publicly verified | H41: No reliable company-specific total, round count or last financing date found in reviewed sources. | I41: S121, S122, S001
A42: IN037 | B42: MemSmart | F42: Unverified | G42: Not publicly verified | H42: No reliable company-specific total, round count or last financing date found in reviewed sources. | I42: S123, S001
A43: IN038 | B43: Quanfluence | C43: 2 | D43: 1 | E43: 45644 | F43: Day | G43: pi Ventures, Golden Sparrow, Reena Dayal and others | H43: USD 2 Mn seed equity. Government grants excluded. | I43: S124, S125, S126, S001
A44: IN039 | B44: TriSpace Technologies | F44: Unverified | G44: Not publicly verified | H44: No reliable company-specific total, round count or last financing date found in reviewed sources. | I44: S127, S128, S001
A45: IN040 | B45: LineSemi Technology | F45: Unverified | G45: Not publicly verified | H45: No reliable company-specific total, round count or last financing date found in reviewed sources. | I45: S129, S130, S001
A46: IN041 | B46: Blueberry Semiconductors | F46: Unverified | G46: Not publicly verified | H46: Inc42 classifies as bootstrapped. No external funding amount or lifetime round count independently verified. | I46: S131, S132, S133
A47: IN042 | B47: SignOff Semiconductors | F47: Unverified | G47: Not publicly verified | H47: Inc42 classifies as bootstrapped; no external total verified. | I47: S134, S135, S136
A48: IN043 | B48: Signalchip Innovations | F48: Unverified | G48: Sridhar Vembu; other support needs reconciliation | H48: Investment support disclosed without a reconciled lifetime dollar total or complete round history. | I48: S137, S138, S139, S140, S001
A49: IN044 | B49: Suchi Semicon | F49: Unverified | G49: Promoters / friends and family; full debt/equity split not public | H49: Promoter/textile-business capital and friends-and-family financing reported. Planned USD 100 Mn investment is project capex, not VC raised. | I49: S141, S142, S143, S144
A50: IN045 | B50: RRP Electronics | F50: Unverified | G50: Not publicly verified | H50: No reliable company-specific total, round count or last financing date found in reviewed sources. | I50: S145, S146, S147
A51: IN046 | B51: Ceremorphic | C51: 50 | D51: 1 | E51: 44585 | F51: Day | G51: Founders | H51: USD 50 Mn Series A funded by founders. Do not characterise as third-party institutional VC capital. | I51: S148, S149, S150
A52: IN047 | B52: Tattvam AI | C52: 1.7 | D52: 1 | E52: 46078 | F52: Day | G52: Seedcamp, EWOR, Entropy, Concept and angels | H52: USD 1.7 Mn pre-seed. | I52: S151
A53: IN048 | B53: Aura Semiconductor | D53: 1 | E53: 2016-10 | F53: Month | G53: Celesta / Walden Riverwood | H53: One disclosed Series A, amount undisclosed. Asset-sale proceeds are not equity financing. | I53: S152, S153, S154
A54: IN049 | B54: SiCSem | F54: Unverified | G54: Not publicly verified | H54: No reliable company-specific total, round count or last financing date found in reviewed sources. | I54: S155, S156, S157
A55: IN050 | B55: Saankhya Labs | F55: Unverified | G55: Not publicly verified | H55: No reliable company-specific total, round count or last financing date found in reviewed sources. | I55: S158, S159, S001
A56: IN051 | B56: Meukron Technologies | F56: Unverified | G56: Not publicly verified | H56: No reliable company-specific total, round count or last financing date found in reviewed sources. | I56: S160, S161, S162
A57: IN052 | B57: LeadSOC Technologies | F57: Unverified | G57: Not publicly verified | H57: No reliable company-specific total, round count or last financing date found in reviewed sources. | I57: S163, S164, S001
A58: IN053 | B58: BITSILICA | F58: Unverified | G58: Not publicly verified | H58: No reliable company-specific total, round count or last financing date found in reviewed sources. | I58: S165, S166, S001
A59: IN054 | B59: IndieSemiC | C59: 0.7401 | D59: 3 | F59: Unverified | G59: Ducon Consultants, GUSEC / AIC GUSEC (database-listed) | H59: Company Check reports USD 0.7401 Mn across 3 rounds. Instrument mix and latest round date unverified; may include incubator/public seed support. | I59: S167, S168, S169, S170, S171, S001
A60: IN055 | B60: Stteereng Silicon | F60: Unverified | G60: Not publicly verified | H60: Not researched beyond official programme roster. Funding total, rounds and last date are not established. | I60: S001
A61: IN056 | B61: Silicon Support Solution (OPC) | F61: Unverified | G61: Not publicly verified | H61: Not researched beyond official programme roster. Funding total, rounds and last date are not established. | I61: S001
A62: IN057 | B62: Tsilicon | F62: Unverified | G62: Not publicly verified | H62: Not researched beyond official programme roster. Funding total, rounds and last date are not established. | I62: S001
A63: IN058 | B63: Semiksha Semiconductors | F63: Unverified | G63: Not publicly verified | H63: Not researched beyond official programme roster. Funding total, rounds and last date are not established. | I63: S001
A64: IN059 | B64: iSOC Semiconductors | F64: Unverified | G64: Not publicly verified | H64: Not researched beyond official programme roster. Funding total, rounds and last date are not established. | I64: S001
A65: IN060 | B65: PrimeSOC Technologies LLP | F65: Unverified | G65: Not publicly verified | H65: Not researched beyond official programme roster. Funding total, rounds and last date are not established. | I65: S001
A66: IN061 | B66: Ciliconchip Circuit | F66: Unverified | G66: Not publicly verified | H66: Not researched beyond official programme roster. Funding total, rounds and last date are not established. | I66: S001
A67: IN062 | B67: Memrym Solutions India | F67: Unverified | G67: Not publicly verified | H67: Not researched beyond official programme roster. Funding total, rounds and last date are not established. | I67: S001
A68: IN063 | B68: MAXVY Technologies | F68: Unverified | G68: Not publicly verified | H68: Not researched beyond official programme roster. Funding total, rounds and last date are not established. | I68: S001
A69: IN064 | B69: Trellisign Tech. | F69: Unverified | G69: Not publicly verified | H69: Not researched beyond official programme roster. Funding total, rounds and last date are not established. | I69: S001
A70: IN065 | B70: Semicon Design Technologies | F70: Unverified | G70: Not publicly verified | H70: Not researched beyond official programme roster. Funding total, rounds and last date are not established. | I70: S001
A71: IN066 | B71: Signitude | F71: Unverified | G71: Not publicly verified | H71: Not researched beyond official programme roster. Funding total, rounds and last date are not established. | I71: S001
... A125: IN120 | B125: CraftifAI Technologies | F125: Unverified | G125: Not publicly verified | H125: No reliable company-specific total, round count or last financing date found in reviewed sources. | I125: S174

Sheet Funding events
A2: Disclosed financing events
A3: Incremental extensions are separated from full round sizes. Incomplete histories are explicitly marked in Funding; dates reflect announcement precision.
A5: Company | B5: Round / event | C5: Announcement / closing date | D5: Incremental USD Mn | E5: Original INR crore | F5: Instrument / classification | G5: Reconciliation note | H5: Source IDs
A6: Mindgrove Technologies | B6: Seed | C6: 2023-02 | D6: 2.32 | F6: Equity | G6: Disclosed seed round. | H6: S002, S003, S004, S005, S006, S001
A7: Mindgrove Technologies | B7: Series A | C7: 2024-12 | D7: 8 | F7: Equity | G7: Separate financing round. | H7: S002, S003, S004, S005, S006, S001
A8: Vervesemi Microelectronics | B8: Series A | C8: 46071 | D8: 10 | F8: Equity | G8: Earlier funding not reconciled. | H8: S007, S008, S009, S010, S001
A9: FermionIC Design | B9: Disclosed round | C9: 2024 | D9: 6 | F9: Equity | G9: Month conflicts between sources; year only. | H9: S011, S012, S013, S014, S015, S016, S001
A10: InCore Semiconductors | B10: Seed | C10: 2023-05 | D10: 3 | F10: Equity | G10: USD 2.99 Mn database figure rounded to USD 3 Mn. | H10: S017, S018, S019, S020, S021, S001
A11: Maieutic Semiconductors | B11: Seed initial close | C11: 45841 | D11: 4.15 | F11: Equity | G11: Part of the seed round later expanded to USD 6 Mn. | H11: S022, S023, S024, S025, S001
A12: Maieutic Semiconductors | B12: Seed extension | C12: 45951 | D12: =6-4.15 -> 1.85 | F12: Equity extension | G12: Incremental amount derived as 6.00 minus 4.15; not a second independent seed round. | H12: S022, S023, S024, S025, S001
A13: C2i Semiconductors | B13: Seed | C13: 45604 | D13: 4 | F13: Equity | G13: Announcement in November; investor timeline says October close. | H13: S026, S027, S028, S029, S001
A14: C2i Semiconductors | B14: Series A initial close | C14: 46069 | D14: 15 | F14: Equity | G14: Part of expanded Series A. | H14: S026, S027, S028, S029, S001
A15: C2i Semiconductors | B15: Series A extension | C15: 46169 | D15: =16.7-15 -> 1.7 | F15: Equity extension | G15: Incremental amount derived as 16.70 minus 15.00. Acquisition consideration excluded. | H15: S026, S027, S028, S029, S001
A16: Agnit Semiconductors | B16: Angel | C16: 2021 | D16: 1.3 | F16: Equity — historical report | G16: Older event omitted from some database totals; cap-table confirmation required. | H16: S030, S031, S032, S033
A17: Agnit Semiconductors | B17: Seed | C17: 2024-10 | D17: 3.5 | F17: Equity | G17: USD 3.5 Mn reported. | H17: S030, S031, S032, S033
A18: Agnit Semiconductors | B18: Seed extension | C18: 2026-03 | D18: 2.6 | F18: Equity extension | G18: 3 funding events including 2021 angel, not necessarily 3 priced institutional rounds. | H18: S030, S031, S032, S033
A19: Netrasemi | B19: Seed | E19: 8.3 | F19: Equity — reported | G19: Date not verified. INR is source currency. | H19: S034, S035, S036, S037, S038, S001
A20: Netrasemi | B20: Pre-Series A | C20: 2024-12 | E20: 10 | F20: Equity | G20: Do not convert each event using an invented current FX rate. | H20: S034, S035, S036, S037, S038, S001
A21: Netrasemi | B21: Series A | C21: 45862 | E21: 107 | F21: Equity | G21: USD total in Funding tab uses reported Tracxn total, not a conversion of this row. | H21: S034, S035, S036, S037, S038, S001
A22: BigEndian Semiconductors | B22: Seed | C22: 2024 | D22: 3 | F22: Equity | G22: USD 3 Mn. | H22: S039, S040, S041, S001
A23: BigEndian Semiconductors | B23: Pre-Series A | C23: 46148 | D23: 6 | F23: Equity | G23: USD 6 Mn. | H23: S039, S040, S041, S001
A24: HrdWyr | B24: Series A | C24: 46154 | D24: 13 | F24: Disclosed private financing | G24: See Funding tab for completeness and instrument limitations. | H24: S051, S052, S053
A25: Agrani Labs | B25: Seed announcement | C25: 46050 | D25: 8 | F25: Disclosed private financing | G25: See Funding tab for completeness and instrument limitations. | H25: S054, S055
A26: Sophrosyne Technologies | B26: Seed | C26: 45982 | D26: 2 | F26: Disclosed private financing | G26: See Funding tab for completeness and instrument limitations. | H26: S074, S075, S001
A27: optoML | B27: Pre-Series A / seed | C27: 46077 | D27: 1.8 | F27: Disclosed private financing | G27: See Funding tab for completeness and instrument limitations. | H27: S113, S114, S115, S116, S117, S001
A28: CIMware Technologies | B28: Pre-Series A | C28: 45840 | D28: 2.3 | F28: Disclosed private financing | G28: See Funding tab for completeness and instrument limitations. | H28: S118, S119, S001
A29: Quanfluence | B29: Seed | C29: 45644 | D29: 2 | F29: Disclosed private financing | G29: See Funding tab for completeness and instrument limitations. | H29: S124, S125, S126, S001
A30: Tattvam AI | B30: Pre-seed | C30: 46078 | D30: 1.7 | F30: Disclosed private financing | G30: See Funding tab for completeness and instrument limitations. | H30: S151
A31: Ceremorphic | B31: Founder-financed Series A | C31: 44585 | D31: 50 | F31: Disclosed private financing | G31: See Funding tab for completeness and instrument limitations. | H31: S148, S149, S150
A32: Calligo Technologies | B32: Pre-Series A | C32: 45754 | D32: 1.1 | F32: Disclosed private financing | G32: See Funding tab for completeness and instrument limitations. | H32: S046, S047, S048, S049, S050, S001
A33: SandLogic Technologies | B33: Disclosed funding | C33: 2022-02 | D33: 4 | F33: Disclosed private financing | G33: See Funding tab for completeness and instrument limitations. | H33: S099, S100, S101, S102, S001
A34: DV2JS Innovation / 3rdiTech | B34: Convertible note | C34: 44061 | D34: 0.11 | F34: Disclosed private financing | G34: See Funding tab for completeness and instrument limitations. | H34: S066, S067, S068, S001
A35: Sensesemi Technologies | B35: Seed | C35: 46044 | D35: 2.7 | E35: 25 | F35: Equity | G35: USD approximation as reported; original INR 25 crore. | H35: S056, S057, S001
A36: Aheesa Digital Innovations | B36: TNIFMC agreement | C36: 46093 | E36: 20 | F36: Public-fund equity | G36: Part of about INR 40 crore cumulative 2026 funding reported by PIB. Remaining capital has no separately verified event date. Not a subsidy. | H36: S058, S059, S060, S061, S001
A37: SimYog Technology | B37: Series A | C37: 45274 | D37: 2.4 | E37: 20 | F37: Equity | G37: Latest disclosed round only; earlier rounds omitted here where exact dates are unresolved. | H37: S103, S104, S105, S106

Sheet Founders
A2: Founders and relevant experience
A3: Founder status is distinguished from CEO, adviser and director status. Unverified full founding teams are flagged.
A5: ID | B5: Company | C5: Founders / role qualification | D5: Relevant background | E5: Repeat founder / professor / employer flags | F5: Source IDs
A6: IN001 | B6: Mindgrove Technologies | C6: Shashwath T R; Sharan Srinivas J (also known as Sharan Jagathrakshakan) | D6: Engineering founders with embedded-computing experience. IIT Madras incubation and SHAKTI ecosystem. Do not confuse Sharan with the Perplexity founder. | E6: Technical founders; IIT Madras ecosystem | F6: S002, S003, S004, S005, S006, S001
A7: IN002 | B7: Vervesemi Microelectronics | C7: Rakesh Malik; Pratap Narayan Singh | D7: Malik previously held senior roles at STMicroelectronics. Singh worked on converters at STMicroelectronics and on audio/power at Wolfson. Their experience is directly relevant to precision analog design. | E7: Ex-global semiconductor employees; experienced founders | F7: S007, S008, S009, S010, S001
A8: IN003 | B8: FermionIC Design | C8: Gautam Kumar Singh; Prasun Bhattacharyya; Abhra Bagchi; Shabaaz Syed | D8: Experienced RF, mixed-signal and chip-integration team. Individual prior employers and full employment chronology require confirmation. | E8: Experienced semiconductor founders | F8: S011, S012, S013, S014, S015, S016, S001
A9: IN004 | B9: InCore Semiconductors | C9: G S Madhusudan; Neel Gala; Arjun Menon; Gautam Doshi | D9: Team emerged from the IIT Madras SHAKTI processor ecosystem. Madhusudan combines industry and systems experience; Gala and Menon bring processor research/design expertise. Professor V. Kamakoti is an ecosystem mentor, not automatically a founder. | E9: Research-to-commercialisation; experienced processor team | F9: S017, S018, S019, S020, S021, S001
A10: IN005 | B10: Maieutic Semiconductors | C10: Gireesh Rajendran; Ashish Lachhwani; Rakesh Kumar; Krishna Sankar | D10: Founding team includes Steradian entrepreneurs whose radar business was acquired by Renesas in 2022, alongside analog-design expertise. Prior exit is evidence of execution, not a promised repeat outcome. | E10: Repeat founders; prior semiconductor exit | F10: S022, S023, S024, S025, S001
A11: IN006 | B11: C2i Semiconductors | C11: Ram Anant; Preetam Tadeparthy; Vikram Gakhar; B S Dattatreya. Reporting also identifies Harsha S B and Muthusubramanian N V as co-founders. | D11: Former Texas Instruments power and analog executives. Founders’ experience spans control, mixed-signal and power design. | E11: Ex-Texas Instruments; announced strategic exit | F11: S026, S027, S028, S029, S001
A12: IN007 | B12: Agnit Semiconductors | C12: Hareesh Chandrasekar; Madhusudan Atre; Mayank Shrivastava; Digbijoy Nath; Muralidharan Rangarajan; Shankar Kumar Selvaraja; Srinivasan Raghavan | D12: IISc faculty/research spin-out supported by experienced semiconductor leadership. Combines device/materials research with commercialisation expertise. | E12: Professor founders; research spin-out; industry veteran | F12: S030, S031, S032, S033
A13: IN008 | B13: Netrasemi | C13: Jyothis Indirabhai; Sreejith Varma; Deepa Geetha | D13: Experienced semiconductor team based in Thiruvananthapuram. Detailed individual prior-employer chronology remains to be independently checked. | E13: Experienced semiconductor founders | F13: S034, S035, S036, S037, S038, S001
A14: IN009 | B14: BigEndian Semiconductors | C14: Sunil Kumar; Renuka Prasad; Harpreet Wadhawan; Dinesh Annayya; Kanagaraju Ponnusamy; Jansen Cheng (reported founding team) | D14: Team experience includes Arm, Intel and Broadcom. Verify each founder’s role and IP-assignment history. | E14: Ex-global semiconductor team | F14: S039, S040, S041, S001
A15: IN010 | B15: Morphing Machines | C15: S K Nandy; Ranjani Narayan; Deepak Shapeti (current company founding/leadership team) | D15: IISc research origins with academic and processor-architecture expertise. Deepak Shapeti joined the commercial leadership later than the original 2005 foundation. | E15: Professor/research founders; long development history | F15: S042, S043, S044, S045, S001
A16: IN011 | B16: Calligo Technologies | C16: Anantha Padmanabha Kinnal; Rajaraman Subramanian | D16: Experienced computing/semiconductor entrepreneurs. Detailed prior employment requires confirmation. | E16: Experienced technical founders | F16: S046, S047, S048, S049, S050, S001
... A125: IN120 | B125: CraftifAI Technologies | C125: Not publicly verified | D125: Not publicly verified | E125: Not publicly verified | F125: S174

Sheet Products and readiness
A2: Products, Indian applications and readiness
A3: A tape-out sends a design for manufacture. Working samples, customer qualification and repeat volume shipments are separate milestones.
A5: ID | B5: Company | C5: Product / service detail | D5: Application in the Indian economy | E5: Latest evidenced readiness | F5: Readiness category | G5: Source IDs
A6: IN001 | B6: Mindgrove Technologies | C6: SecureIoT S2401 combines a RISC-V processor with memory, security and peripheral functions. Evaluation boards support firmware development. Vision-series chips target camera and other on-device visual processing. | D6: Local controllers for smart meters, access control, industrial devices and cameras can reduce dependence on imported controllers and improve local technical support. | E6: SecureIoT first silicon was demonstrated in May 2024; evaluation board launched in March 2025. September 2026 reporting describes customer trials and first revenue expected in FY27. Later-2026 roadmap entries are targets, not proof of shipment. | F6: Working silicon / customer trials | G6: S002, S003, S004, S005, S006, S001
A7: IN002 | B7: Vervesemi Microelectronics | C7: Analog and mixed-signal IP and ICs for accurate measurement, motor control, energy metering and power conversion. The DLI programme supports a mixed-signal motor-control microcontroller. | D7: More efficient fans and appliances, accurate smart meters, industrial motor drives and reliable aerospace instrumentation. | E7: August 2026 PIB update confirms first-pass BLDC-controller silicon using InCore IP and a motor-driver chip. Earlier fabricated analog products were under evaluation. Qualified volume shipments are not verified. | F7: Fabricated silicon / evaluation | G7: S007, S008, S009, S010, S001
A8: IN003 | B8: FermionIC Design | C8: Radio-frequency chips and interface IP. DLI project is an 8–12 GHz four-channel gain/phase-control chip for electronically steered antenna arrays. Beamformer and front-end products support radar and satellite links. | D8: Local radar electronics, defence communications, satellite terminals and telecom equipment can substitute imported RF components. | E8: Company demonstrated a prototype antenna tile using its own chips in early 2026. GlobalFoundries manufacturing partnership announced June 2026. Mass-production volumes are not publicly verified. | F8: Prototype / foundry partnership | G8: S011, S012, S013, S014, S015, S016, S001
A9: IN004 | B9: InCore Semiconductors | C9: Configurable RISC-V processor IP and automated system-on-chip generation. Customers license reusable processor designs and integrate them into their own chips rather than buying a general-purpose InCore chip. | D9: Domestic IP ownership for metering, cameras, industrial controllers and future custom chips. Enables Indian companies to design products without building a CPU team from scratch. | E9: Company reports a six-core test chip and silicon validation of its SoC generator. September 2026 company material shows partners’ taped-out chips using InCore IP. This supports IP validation, not a disclosed royalty run rate. | F9: Silicon-validated IP | G9: S017, S018, S019, S020, S021, S001
A10: IN005 | B10: Maieutic Semiconductors | C10: AI-assisted analog and mixed-signal circuit-design software. Engineers can use an assistant to explore designs, review circuits and reduce repetitive development work. | D10: Can improve productivity of India’s chip-design teams and help smaller fabless companies cope with scarce experienced analog engineers. | E10: Product development and planned rollout reported. Independent production-workflow benchmarks and paying-customer deployment evidence were not verified. A proprietary chip tape-out is not the right readiness test for this software. | F10: Software development / commercial validation pending | G10: S022, S023, S024, S025, S001
A11: IN006 | B11: C2i Semiconductors | C11: Manas digital multiphase controller and Sarayu smart power stage. Software-defined voltage regulation delivers power close to AI processors. | D11: Supports efficient AI servers and data-centre power systems. Indian adoption depends on server-design qualification rather than data-centre construction alone. | E11: First designs sent to foundries in 2026 and smart-power-stage tape-out announced in May. Independent mass-production qualification not verified. | F11: Tape-out / strategic acquisition | G11: S026, S027, S028, S029, S001
A12: IN007 | B12: Agnit Semiconductors | C12: Gallium nitride (GaN) materials, RF devices and related process technology. Focus includes high-frequency/high-power chips for communications and defence. | D12: Local RF supply for radar, telecom and strategic electronics. Power-device applications are a longer-term option and should not be confused with qualified charger or EV products. | E12: Pilot projects and process development reported. March 2026 reporting targeted commercial shipments for July 2027; five pilots reported in August 2026. Do not treat target volume as actual sales. | F12: Pilot / manufacturing scale-up | G12: S030, S031, S032, S033
A13: IN008 | B13: Netrasemi | C13: Edge-AI system-on-chips for cameras, robotics and industrial devices. A2000 and R1000 product programmes combine local AI, video processing and connectivity. | D13: Processes camera and sensor data locally, reducing network dependence and supporting surveillance, automation and robotics. | E13: August 2026 PIB update confirms successful testing of a 12 nm vision SoC. Customer trials were reported in May. Commercial volume production remains unverified. | F13: First chip / trials; next chip taped out | G13: S034, S035, S036, S037, S038, S001
A14: IN009 | B14: BigEndian Semiconductors | C14: Secure video-processing and edge-AI chips for surveillance cameras and related connected equipment. | D14: Supports indigenous camera electronics and local control over security-sensitive silicon and firmware. | E14: Investors report successful tape-out and progression from test silicon towards production-ready devices in 2026. Production qualification not independently confirmed. | F14: Tape-out / test silicon | G14: S039, S040, S041, S001
A15: IN010 | B15: Morphing Machines | C15: REDEFINE reconfigurable many-core compute architecture, processor IP and accelerator-card ecosystem. Aims to adapt hardware resources to changing compute workloads. | D15: Potential acceleration for industrial, defence and scientific workloads, subject to real application benchmarks and software portability. | E15: Company roadmap targeted a test chip in Q3 2026. Verified completed silicon and volume deployment not located; elapsed target date is not completion. | F15: Development / silicon confirmation pending | G15: S042, S043, S044, S045, S001
A16: IN011 | B16: Calligo Technologies | C16: TUNGA RISC-V processor with POSIT arithmetic and accelerator-card/software stack. POSIT is an alternative numeric representation intended to improve computing efficiency. | D16: Scientific computing, engineering simulations and specialised AI workloads; value must be demonstrated against current CPU/GPU systems on complete applications. | E16: TUNGA first-generation chip and early-customer testing reported. Independent deployment volumes and benchmark reproducibility not verified. | F16: Working chip / early testing | G16: S046, S047, S048, S049, S050, S001
... A125: IN120 | B125: CraftifAI Technologies | C125: Named in September 2026 SEMICON startup competition coverage. Detailed product specification not verified. | D125: Not publicly verified | E125: Award/selection does not establish deployment readiness. | F125: Not established | G125: S174

Sheet Customers and alliances
A2: Customer evidence, alliances and potential beneficiaries
A3: Confirmed relationship descriptions and analyst-proposed beneficiaries are kept separate. Potential beneficiary lists are not customer lists.
A5: ID | B5: Company | C5: Target customer segment | D5: Named customers / evidence limits | E5: Commercial conviction / next test | F5: Strategic alliances and their limits | G5: Potential large / listed Indian beneficiaries (inference) | H5: Indian fab / OSAT / compound-fab fit (inference) | I5: Source IDs
A6: IN001 | B6: Mindgrove Technologies | C6: Device manufacturers, meter makers, camera and industrial-equipment designers. | D6: Bosch BGSW alliance and Pinetics integration agreement are named commercial-development signals. Metering, biometric and CCTV trials are reported. Recurring volume orders remain unverified. PRAMA India is a further named camera-development partner. | E6: Conditional: working silicon and integration partners reduce engineering risk. Require purchase orders, qualification reports and cash collections before underwriting a volume ramp. | F6: Bosch BGSW MoU / startup alliance; Pinetics integration. Neither establishes a guaranteed minimum purchase. PRAMA India agreement explores Vision SoC use in CCTV cameras; not a volume purchase commitment. | G6: Genus Power, HPL Electric, Dixon, Kaynes Technology and BEL are prospective adopters, not confirmed customers. | H6: Potential packaging/test demand for Kaynes, CG Semi, Suchi or Tata’s packaging business after package qualification. A future Tata silicon-fab port needs compatible node, process IP and redesign; no automatic fit. | I6: S002, S003, S004, S005, S006, S001
A7: IN002 | B7: Vervesemi Microelectronics | C7: Industrial and appliance OEMs, meter manufacturers, space/defence electronics suppliers and chip designers licensing analog IP. | D7: An identified but unnamed space customer was reported by PIB. Public customer names, committed quantities and recurring chip revenue are not established. | E7: Promising product breadth and experienced analog team. Validate which ICs are actually qualified and revenue-producing rather than counting IP blocks as commercial chips. | F7: UMC and TSMC process use is reported by PIB. Samsung SAFE IP participation is reported in Bharat Innovates material; it is an ecosystem relationship, not an offtake contract. InCore processor IP used in BLDC controller, confirmed by PIB in August 2026. | G7: Havells, Crompton, Genus Power, HPL Electric, BEL, HAL and Dixon are prospective adopters. | H7: Potential packaging/test demand for Kaynes, CG Semi, Suchi or Tata’s packaging business after package qualification. A future Tata silicon-fab port needs compatible node, process IP and redesign; no automatic fit. | I7: S007, S008, S009, S010, S001
A8: IN003 | B8: FermionIC Design | C8: Radar, aerospace, satellite-communication and telecom equipment manufacturers; chip-design customers for interface IP. | D8: Company claims Indian and overseas OEM engagements. DigiKey supplier presence provides a named sales channel. No named recurring-volume purchase agreement verified. | E8: Stronger production-route evidence than a design-only project. Diligence must establish qualification, unit economics, order backlog and whether RF components meet defence reliability requirements. | F8: Commercial manufacturing partnership with GlobalFoundries announced 11 June 2026; DigiKey distribution. Qualcomm mentorship is not a customer order. | G8: BEL, HAL, Data Patterns, Astra Microwave, Paras Defence and Tejas Networks are prospective adopters. | H8: Packaging/test opportunity for Kaynes, CG Semi or specialist OSATs, subject to RF process/package qualification. SiGe/GaN designs cannot simply transfer into a standard CMOS fab. | I8: S011, S012, S013, S014, S015, S016, S001
A9: IN004 | B9: InCore Semiconductors | C9: Fabless chip companies, ASIC design houses and OEMs developing custom silicon. | D9: Vervesemi controller silicon uses InCore IP, confirmed by PIB in August 2026. HCL/Tessolve collaborations are also named. Licence fees and recurring royalties remain undisclosed. | E9: Attractive capital efficiency because IP can be licensed repeatedly. Confirm ownership of university-derived IP, paid licences and royalty-bearing designs. | F9: HCL and Tessolve solution collaborations; RISC-V ecosystem. An open instruction-set standard is not an exclusive global-chipmaker alliance. | G9: HCLTech, Cyient, MosChip, Tata Elxsi and L&T Semiconductor Technologies could use processor IP in customer or internal designs. | H9: Indirect enabler: supports customer designs/IP rather than directly filling wafer capacity. Potential users include MosChip, Cyient, HCLTech and L&T Semiconductor Technologies. | I9: S017, S018, S019, S020, S021, S001
A10: IN005 | B10: Maieutic Semiconductors | C10: Analog chip designers, semiconductor product companies and design-services teams. | D10: No named paying customers or recurring software revenue verified. | E10: Founder execution history and reusable software are attractive. Investment depends on paid pilots, measurable engineer time savings and integration with incumbent EDA tools. | F10: UTEC, Endiya and Exfinity are financial investors. The founders’ former Renesas exit is not a current Maieutic–Renesas partnership. | G10: MosChip, Cyient, HCLTech, L&T Semiconductor Technologies and Indian analog design centres are prospective users. | H10: Indirect enabler: supports customer designs/IP rather than directly filling wafer capacity. Potential users include MosChip, Cyient, HCLTech and L&T Semiconductor Technologies. | I10: S022, S023, S024, S025, S001
A11: IN006 | B11: C2i Semiconductors | C11: Global server manufacturers, power-module suppliers and AI infrastructure designers. | D11: No named committed-volume buyer verified before acquisition. Infineon supplies strategic validation and potential access to customers; it is an acquirer, not evidence of existing customer revenue. | E11: Useful exit precedent, but unavailable as a normal independent VC candidate after acquisition agreement. | F11: TDK Ventures strategic investment; Tower Semiconductor / GlobalFoundries fabrication routes. Infineon announced acquisition on 24 August 2026; release expected Q3 closing, separate closing confirmation not located. | G11: Netweb Technologies and Indian server/power-system manufacturers are prospective downstream beneficiaries. Tata Communications and Reliance data centres could benefit indirectly. | H11: Potential packaging/test demand for Kaynes, CG Semi, Suchi or Tata’s packaging business after package qualification. A future Tata silicon-fab port needs compatible node, process IP and redesign; no automatic fit. | I11: S026, S027, S028, S029, S001
A12: IN007 | B12: Agnit Semiconductors | C12: Defence and telecom equipment manufacturers, RF module companies and wafer/device customers. | D12: Five pilots reported, but counterparties and binding volume orders not publicly verified. | E12: Strong differentiated science; higher process, yield and capital risk. Require reproducible yields, paid pilot conversion and a funding plan that does not depend on an unapproved fab subsidy. | F12: IISc GaN ecosystem; iDEX development relationship. No purchase commitment from a global semiconductor giant verified. | G12: BEL, Astra Microwave, Data Patterns and Tejas Networks are prospective users; SiCSem and RIR are adjacent compound-semiconductor companies, not interchangeable GaN foundries. | H12: SiCSem (Archean) and RIR are relevant compound-power ecosystem peers. GaN and SiC processes are different; no automatic foundry compatibility or customer relationship. | I12: S030, S031, S032, S033
A13: IN008 | B13: Netrasemi | C13: Camera makers, robotics companies and industrial/consumer device OEMs. | D13: Customer trials reported; Zoho is an investor and cannot be treated as guaranteed offtake. Named volume customers not verified. | E13: Meaningful capital and product progress, but commercial qualification and software adoption remain key risks. | F13: TSMC manufacturing/process relationship; Zoho strategic investment. No guaranteed purchase volumes verified. | G13: Dixon, Kaynes Technology, BEL, Tata Elxsi and industrial OEMs are prospective adopters. | H13: Potential packaging/test demand for Kaynes, CG Semi, Suchi or Tata’s packaging business after package qualification. A future Tata silicon-fab port needs compatible node, process IP and redesign; no automatic fit. | I13: S034, S035, S036, S037, S038, S001
A14: IN009 | B14: BigEndian Semiconductors | C14: Surveillance camera brands, camera design manufacturers and security-equipment OEMs. | D14: Unnamed OEM relationships reported by investors. No named firm volume order verified. | E14: Clear initial use case, but needs competitive image quality, software compatibility and OEM qualification against entrenched suppliers. | F14: Not publicly verified | G14: Dixon, Kaynes, BEL and Indian surveillance manufacturers are prospective adopters. | H14: Potential packaging/test demand for Kaynes, CG Semi, Suchi or Tata’s packaging business after package qualification. A future Tata silicon-fab port needs compatible node, process IP and redesign; no automatic fit. | I14: S039, S040, S041, S001
A15: IN010 | B15: Morphing Machines | C15: Compute OEMs, defence research users, chip companies and specialised high-performance computing customers. | D15: Research and proof-of-concept engagements reported; named recurring commercial buyers not verified. | E15: Scientific differentiation is plausible, but long development history and software ecosystem make commercial validation essential. | F15: Not publicly verified | G15: BEL, HAL, Netweb, HCLTech and Cyient are prospective adopters/integration channels. | H15: Potential packaging/test demand for Kaynes, CG Semi, Suchi or Tata’s packaging business after package qualification. A future Tata silicon-fab port needs compatible node, process IP and redesign; no automatic fit. | I15: S042, S043, S044, S045, S001
A16: IN011 | B16: Calligo Technologies | C16: HPC operators, research institutions, server/accelerator OEMs and scientific-computing users. | D16: Early evaluations reported; customer identities and binding backlog not verified. | E16: Working silicon helps. Unusual arithmetic creates a software-porting and customer-adoption hurdle. | F16: Not publicly verified | G16: Netweb Technologies, HCLTech, BEL and Indian research-compute suppliers are prospective adopters. | H16: Potential packaging/test demand for Kaynes, CG Semi, Suchi or Tata’s packaging business after package qualification. A future Tata silicon-fab port needs compatible node, process IP and redesign; no automatic fit. | I16: S046, S047, S048, S049, S050, S001
... A22: IN017 | B22: MOSart Semi | C22: Battery-pack makers, EV OEMs and energy-storage system manufacturers. | D22: No named purchase order or recurring product revenue verified. | E22: Battery management has clear demand, but automotive qualification and safety requirements create long sales cycles. | F22: Not publicly verified | G22: Exide Industries, Amara Raja Energy & Mobility, Tata Motors, M&M and TVS Motor are prospective users. | H22: Potential packaging/test demand for Kaynes, CG Semi, Suchi or Tata’s packaging business after package qualification. A future Tata silicon-fab port needs compatible node, process IP and redesign; no automatic fit. | I22: S064, S065
A23: IN018 | B23: DV2JS Innovation / 3rdiTech | C23: Defence/imaging equipment OEMs and specialist camera manufacturers. | D23: Strategic-government engagement and consortium MoUs exist; public recurring orders not verified. | F23: 2025 MoU with Kaynes Semicon, SPARSHIQ and consortium partners. Indo-US Bharat Semi/3rdiTech fab collaboration announced in 2024 is not proof of an operational fab. | G23: BEL, HAL, Data Patterns and Kaynes are prospective users/packaging participants; Kaynes MoU is confirmed at consortium level. | H23: Potential packaging/test demand for Kaynes, CG Semi, Suchi or Tata’s packaging business after package qualification. A future Tata silicon-fab port needs compatible node, process IP and redesign; no automatic fit. | I23: S066, S067, S068, S001
A24: IN019 | B24: Aryabhata Circuits and Research Labs | C24: Tyre manufacturers, automotive electronics suppliers, fleet-system providers and vehicle OEMs. | D24: No named purchase order or recurring product revenue verified. | E24: Specific automotive pain point; automotive reliability, tyre integration and a paying tier-one partner are gating items. | F24: Not publicly verified | G24: MRF, Apollo Tyres, CEAT, JK Tyre, Tata Motors and M&M are prospective users. | H24: Potential packaging/test demand for Kaynes, CG Semi, Suchi or Tata’s packaging business after package qualification. A future Tata silicon-fab port needs compatible node, process IP and redesign; no automatic fit. | I24: S069, S070, S001
A25: IN020 | B25: Silizium Circuits | C25: Telecom, navigation, satellite-equipment and industrial-IoT manufacturers. | D25: C-DOT is a named development counterparty; this is stronger than an unnamed pipeline but not equivalent to commercial chip volume. | F25: C-DOT TTDF contract; IIT Kanpur research collaboration; NXP/FabCI accelerator association is not an offtake agreement. | G25: BEL, Tejas, HFCL, Data Patterns and navigation-equipment OEMs are prospective adopters. | H25: Packaging/test opportunity for Kaynes, CG Semi or specialist OSATs, subject to RF process/package qualification. SiGe/GaN designs cannot simply transfer into a standard CMOS fab. | I25: S071, S072, S073, S001
A26: IN021 | B26: Sophrosyne Technologies | C26: Wearable brands, medical-device OEMs and health-monitoring equipment suppliers. | D26: No named recurring-volume customer verified. | E26: Healthcare sensing is a useful niche, but chip performance and medical-system validation must be distinguished. | F26: Not publicly verified | G26: Dixon, Syrma SGS and Indian medical-electronics manufacturers are prospective users. | H26: Potential packaging/test demand for Kaynes, CG Semi, Suchi or Tata’s packaging business after package qualification. A future Tata silicon-fab port needs compatible node, process IP and redesign; no automatic fit. | I26: S074, S075, S001
A27: IN022 | B27: MMRFIC Technology | C27: Defence, aerospace, space and telecom equipment makers. | D27: Sansera Engineering’s strategic investment is a named relationship. Product purchase commitments not verified. | F27: Sansera Engineering strategic investment; not a global-semiconductor-giant purchase agreement. | G27: Sansera is a strategic investor. BEL, Astra Microwave and Data Patterns are prospective RF-system adopters. | H27: Packaging/test opportunity for Kaynes, CG Semi or specialist OSATs, subject to RF process/package qualification. SiGe/GaN designs cannot simply transfer into a standard CMOS fab. | I27: S076, S077, S078, S001
A28: IN023 | B28: MBit Wireless | C28: Cellular-module suppliers, IoT device makers and telecom-equipment OEMs. | D28: No named purchase order or recurring product revenue verified. | E28: Confirm IP ownership across Indian/US entities, modem certification and module-maker design wins. | F28: Not publicly verified | G28: Genus Power, HPL Electric, Tejas, HFCL and ITI are prospective adopters. | H28: Packaging/test opportunity for Kaynes, CG Semi or specialist OSATs, subject to RF process/package qualification. SiGe/GaN designs cannot simply transfer into a standard CMOS fab. | I28: S079, S080, S001
A29: IN024 | B29: Multi Nano Sense Technologies | C29: Hydrogen producers, industrial plants, safety-equipment OEMs and gas-sensor integrators. | D29: Company lists clientele and demonstrations; specific recurring contract values and customer concentration not verified. | E29: Existing sensor products offer a nearer revenue path than a wholly new SoC. Verify field calibration, certifications and customer renewals. | F29: University of Cambridge technology licensing and IIT Bombay fabrication collaboration; not a global chipmaker offtake. | G29: Reliance Industries, L&T, NTPC, Indian Oil, GAIL and industrial gas/equipment companies are prospective users. | H29: Potential packaging/test demand for Kaynes, CG Semi, Suchi or Tata’s packaging business after package qualification. A future Tata silicon-fab port needs compatible node, process IP and redesign; no automatic fit. | I29: S081, S082, S083, S084, S001
A30: IN025 | B30: Incise Infotech | C30: Fabless companies, semiconductor suppliers, lighting OEMs and embedded-system customers. | D30: No named purchase order or recurring product revenue verified. | E30: Assess services margins and reusable-IP ownership separately from the LED product opportunity. | F30: Listed on Andes Technology design-services partner page; partnership does not establish order volumes. | G30: Havells, Dixon, HCLTech, Cyient and MosChip are prospective customers/partners; some may also compete. | H30: Indirect enabler: supports customer designs/IP rather than directly filling wafer capacity. Potential users include MosChip, Cyient, HCLTech and L&T Semiconductor Technologies. | I30: S085, S086, S087, S001
A31: IN026 | B31: WiSig Networks | C31: Telecom-equipment suppliers, operators, private-network customers and IoT module makers. | D31: C-DOT is a named development supporter; field sites are reported. Historical reporting explicitly noted weak commercial chip uptake. | E31: Strong technical pedigree but customer conversion is the gating risk, not simply another tape-out. | F31: CEVA Dragonfly NB2 IP licence; trials with Sharp Semiconductor Innovation Corporation and IIT Hyderabad; C-DOT/VVDN collaboration. | G31: Tejas, HFCL, ITI, Genus Power and industrial-network integrators are prospective adopters. | H31: Packaging/test opportunity for Kaynes, CG Semi or specialist OSATs, subject to RF process/package qualification. SiGe/GaN designs cannot simply transfer into a standard CMOS fab. | I31: S088, S089, S090, S091, S001
A32: IN027 | B32: Aagyavision | C32: Security, radar, industrial-sensing and telecom-system OEMs. | D32: No named recurring-volume buyer verified. | E32: Clear sensing niche and academic moat. Require field false-alarm performance and paid pilot conversion. | F32: AMD CSR grant through IISc FSID announced June 2025. This is non-dilutive corporate support, not AMD buying chips. | G32: BEL, Data Patterns, Astra Microwave, L&T and Adani infrastructure businesses are prospective users. | H32: Packaging/test opportunity for Kaynes, CG Semi or specialist OSATs, subject to RF process/package qualification. SiGe/GaN designs cannot simply transfer into a standard CMOS fab. | I32: S092, S093, S094, S001
A33: IN028 | B33: Chipspirit Technologies | C33: Defence/security agencies, critical-infrastructure operators and semiconductor-design customers. | D33: Indian Defence is a named co-development counterparty, not proof of a recurring procurement order. | E33: Procurement and product-certification evidence is needed to separate a defence demonstration from a scalable business. | F33: Not publicly verified | G33: BEL, HAL, L&T and critical-infrastructure systems integrators are prospective users. | H33: Indirect enabler: supports customer designs/IP rather than directly filling wafer capacity. Potential users include MosChip, Cyient, HCLTech and L&T Semiconductor Technologies. | I33: S095, S096, S097, S098, S001
A34: IN029 | B34: SandLogic Technologies | C34: Consumer-device makers, industrial OEMs and enterprises deploying AI. | D34: BW Tech hardware co-development is named; commercial chip customers and orders not verified. | E34: Existing software access could aid distribution, but chip power/performance and actual silicon need verification. | F34: BW Tech co-development; HPE accelerator association is not a chip purchase guarantee. | G34: Dixon, Kaynes, Tata Elxsi and connected-device manufacturers are prospective users. | H34: Potential packaging/test demand for Kaynes, CG Semi, Suchi or Tata’s packaging business after package qualification. A future Tata silicon-fab port needs compatible node, process IP and redesign; no automatic fit. | I34: S099, S100, S101, S102, S001
A35: IN030 | B35: SimYog Technology | C35: Automotive/electronics engineering teams, component suppliers and test organisations. | D35: Bosch engineering arm is a named investor and development ecosystem participant. Customer revenue and renewal cohorts not publicly verified. | E35: Capital-efficient tooling with a measurable engineering ROI; assess renewal quality and solver differentiation. | F35: Bosch investment; Mela, 1Crowd and Ideaspring backing. Bosch participation is not a universal purchase guarantee. | G35: Bosch India, Tata Elxsi, KPIT, L&T Technology Services and automotive suppliers are prospective users. | H35: Indirect enabler: supports customer designs/IP rather than directly filling wafer capacity. Potential users include MosChip, Cyient, HCLTech and L&T Semiconductor Technologies. | I35: S103, S104, S105, S106
A36: IN031 | B36: Ananant Systems | C36: Telecom-equipment manufacturers, operators and private-network integrators. | D36: No named binding volume orders verified. | E36: Relevant founder experience; requires evidence of paid design wins and exportable standards-compliant products. | F36: Not publicly verified | G36: Tejas, HFCL, ITI and BEL are prospective users. | H36: Packaging/test opportunity for Kaynes, CG Semi or specialist OSATs, subject to RF process/package qualification. SiGe/GaN designs cannot simply transfer into a standard CMOS fab. | I36: S107, S108, S109, S001
A37: IN032 | B37: VASBEAM | C37: Satellite terminal, radar and telecom-equipment OEMs. | D37: No named purchase order or recurring product revenue verified. | E37: Demonstrated fabrication is useful; commercial maturity and founder track record need verification. | F37: Not publicly verified | G37: BEL, Astra Microwave, Tejas and Data Patterns are prospective users. | H37: Packaging/test opportunity for Kaynes, CG Semi or specialist OSATs, subject to RF process/package qualification. SiGe/GaN designs cannot simply transfer into a standard CMOS fab. | I37: S110, S111, S112, S001
A38: IN033 | B38: optoML | C38: AI device OEMs, industrial-sensing companies and compute infrastructure designers. | D38: No named recurring-volume customer verified. Kaynes is a packaging counterparty, not an end buyer. | E38: Potential efficiency moat, but analog-compute accuracy, software usability and manufacturing variation are material risks. | F38: TSMC process use and Kaynes Semicon assembly/test MoU. | G38: Kaynes is a named packaging partner. Netweb, Dixon and industrial OEMs are prospective adopters. | H38: Potential packaging/test demand for Kaynes, CG Semi, Suchi or Tata’s packaging business after package qualification. A future Tata silicon-fab port needs compatible node, process IP and redesign; no automatic fit. | I38: S113, S114, S115, S116, S117, S001
A39: IN034 | B39: CIMware Technologies | C39: Data-centre operators, enterprises, networking OEMs and infrastructure integrators. | D39: No named purchase order or recurring product revenue verified. | E39: Adjacent systems opportunity. Establish whether defensibility resides in own silicon, software or assembly before assigning chip-IP valuation. | F39: Not publicly verified | G39: Netweb, Tata Communications, Sify and HCLTech are prospective users/integrators. | H39: Potential packaging/test demand for Kaynes, CG Semi, Suchi or Tata’s packaging business after package qualification. A future Tata silicon-fab port needs compatible node, process IP and redesign; no automatic fit. | I39: S118, S119, S001
... A125: IN120 | B125: CraftifAI Technologies | C125: Not publicly verified | D125: Not publicly verified | E125: Discovery lead only. | F125: Not publicly verified | G125: Not publicly verified | H125: Unverified: product, node and package must be established before mapping an Indian fab/OSAT. | I125: S174

Sheet Government support
A2: Government support by company
A3: Approval, project outlay, in-kind tools, public equity and cash disbursement are different. April 2026 DLI roster is a dated baseline.
A5: ID | B5: Company | C5: DLI financial project count | D5: EDA tools approved | E5: Company-specific support and limits | F5: Cash receipt / disbursement status | G5: Source IDs
A6: IN001 | B6: Mindgrove Technologies | C6: 1 | D6: Yes — April 2026 roster | E6: DLI financial-support approval for Vision SoC. Company reports INR 15 crore support; cash disbursement not verified. EDA-tools access separately listed in April 2026. | F6: No verified company-level disbursement ledger obtained. | G6: S002, S003, S004, S005, S006, S001
A7: IN002 | B7: Vervesemi Microelectronics | C7: 1 | D7: Yes — April 2026 roster | E7: First DLI-approved company according to PIB; also C2S support. Approved motor-control project is separate from equity funding; cash receipt not established. EDA-tools access separately listed in April 2026. | F7: No verified company-level disbursement ledger obtained. | G7: S007, S008, S009, S010, S001
A8: IN003 | B8: FermionIC Design | C8: 1 | D8: Yes — April 2026 roster | E8: DLI financial-support project approved in the 1 April 2026 roster. Cash disbursement not verified. No company-specific cash incentive verified. This is not evidence that none exists. EDA-tools access separately listed in April 2026. | F8: No verified company-level disbursement ledger obtained. | G8: S011, S012, S013, S014, S015, S016, S001
A9: IN004 | B9: InCore Semiconductors | C9: 1 | D9: Yes — April 2026 roster | E9: DLI financial-support project approved in the 1 April 2026 roster. Cash disbursement not verified. No company-specific cash incentive verified. This is not evidence that none exists. EDA-tools access separately listed in April 2026. | F9: No verified company-level disbursement ledger obtained. | G9: S017, S018, S019, S020, S021, S001
A10: IN005 | B10: Maieutic Semiconductors | D10: Yes — April 2026 roster | E10: No company-specific cash incentive verified. This is not evidence that none exists. EDA-tools access separately listed in April 2026. | F10: No verified company-level disbursement ledger obtained. | G10: S022, S023, S024, S025, S001
A11: IN006 | B11: C2i Semiconductors | C11: 1 | D11: Yes — April 2026 roster | E11: DLI financial-support project approved in the 1 April 2026 roster. Cash disbursement not verified. No company-specific cash incentive verified. This is not evidence that none exists. EDA-tools access separately listed in April 2026. | F11: No verified company-level disbursement ledger obtained. | G11: S026, S027, S028, S029, S001
A12: IN007 | B12: Agnit Semiconductors | D12: Not established in April roster | E12: MeitY-supported GaN ecosystem incubation; iDEX development support and Karnataka ELEVATE recognition reported. A contemplated fab proposal is not an ISM subsidy approval. | F12: No verified company-level disbursement ledger obtained. | G12: S030, S031, S032, S033
A13: IN008 | B13: Netrasemi | C13: 2 | D13: Yes — April 2026 roster | E13: DLI financial-support project approved in the 1 April 2026 roster. Cash disbursement not verified. No company-specific cash incentive verified. This is not evidence that none exists. EDA-tools access separately listed in April 2026. | F13: No verified company-level disbursement ledger obtained. | G13: S034, S035, S036, S037, S038, S001
A14: IN009 | B14: BigEndian Semiconductors | C14: 1 | D14: Yes — April 2026 roster | E14: DLI financial-support project approved in the 1 April 2026 roster. Cash disbursement not verified. No company-specific cash incentive verified. This is not evidence that none exists. EDA-tools access separately listed in April 2026. | F14: No verified company-level disbursement ledger obtained. | G14: S039, S040, S041, S001
A15: IN010 | B15: Morphing Machines | C15: 1 | D15: Yes — April 2026 roster | E15: DLI financial-support project approved in the 1 April 2026 roster. Cash disbursement not verified. No company-specific cash incentive verified. This is not evidence that none exists. EDA-tools access separately listed in April 2026. | F15: No verified company-level disbursement ledger obtained. | G15: S042, S043, S044, S045, S001
A16: IN011 | B16: Calligo Technologies | C16: 1 | D16: Yes — April 2026 roster | E16: DLI financial-support project approved in the 1 April 2026 roster. Cash disbursement not verified. No company-specific cash incentive verified. This is not evidence that none exists. EDA-tools access separately listed in April 2026. | F16: No verified company-level disbursement ledger obtained. | G16: S046, S047, S048, S049, S050, S001
A17: IN012 | B17: HrdWyr | D17: Not established in April roster | E17: No company-specific cash incentive verified. This is not evidence that none exists. | F17: No verified company-level disbursement ledger obtained. | G17: S051, S052, S053
A18: IN013 | B18: Agrani Labs | D18: Not established in April roster | E18: No company-specific cash incentive verified. This is not evidence that none exists. | F18: No verified company-level disbursement ledger obtained. | G18: S054, S055
A19: IN014 | B19: Sensesemi Technologies | C19: 1 | D19: Yes — April 2026 roster | E19: DLI financial-support project approved in the 1 April 2026 roster. Cash disbursement not verified. No company-specific cash incentive verified. This is not evidence that none exists. EDA-tools access separately listed in April 2026. | F19: No verified company-level disbursement ledger obtained. | G19: S056, S057, S001
A20: IN015 | B20: Aheesa Digital Innovations | C20: 1 | D20: Yes — April 2026 roster | E20: DLI financial-support project approved in the 1 April 2026 roster. Cash disbursement not verified. No company-specific cash incentive verified. This is not evidence that none exists. EDA-tools access separately listed in April 2026. | F20: No verified company-level disbursement ledger obtained. | G20: S058, S059, S060, S061, S001
A21: IN016 | B21: Green PMU Semi | C21: 1 | D21: Yes — April 2026 roster | E21: DLI financial-support project approved in the 1 April 2026 roster. Cash disbursement not verified. No company-specific cash incentive verified. This is not evidence that none exists. EDA-tools access separately listed in April 2026. | F21: No verified company-level disbursement ledger obtained. | G21: S062, S063, S001
A22: IN017 | B22: MOSart Semi | D22: Not established in April roster | E22: No company-specific cash incentive verified. This is not evidence that none exists. | F22: No verified company-level disbursement ledger obtained. | G22: S064, S065
A23: IN018 | B23: DV2JS Innovation / 3rdiTech | C23: 1 | D23: Yes — April 2026 roster | E23: DLI financial-support project approved in the 1 April 2026 roster. Cash disbursement not verified. No company-specific cash incentive verified. This is not evidence that none exists. EDA-tools access separately listed in April 2026. | F23: No verified company-level disbursement ledger obtained. | G23: S066, S067, S068, S001
A24: IN019 | B24: Aryabhata Circuits and Research Labs | C24: 1 | D24: Yes — April 2026 roster | E24: DLI financial-support project approved in the 1 April 2026 roster. Cash disbursement not verified. No company-specific cash incentive verified. This is not evidence that none exists. EDA-tools access separately listed in April 2026. | F24: No verified company-level disbursement ledger obtained. | G24: S069, S070, S001
A25: IN020 | B25: Silizium Circuits | D25: Yes — April 2026 roster | E25: C-DOT TTDF development support; EDA access under DLI. IIT Kanpur joint project grants must not be booked entirely as company cash. | F25: No verified company-level disbursement ledger obtained. | G25: S071, S072, S073, S001
A26: IN021 | B26: Sophrosyne Technologies | C26: 1 | D26: Yes — April 2026 roster | E26: DLI financial-support project approved in the 1 April 2026 roster. Cash disbursement not verified. No company-specific cash incentive verified. This is not evidence that none exists. EDA-tools access separately listed in April 2026. | F26: No verified company-level disbursement ledger obtained. | G26: S074, S075, S001
A27: IN022 | B27: MMRFIC Technology | C27: 1 | D27: Yes — April 2026 roster | E27: DLI financial-support project approved in the 1 April 2026 roster. Cash disbursement not verified. No company-specific cash incentive verified. This is not evidence that none exists. EDA-tools access separately listed in April 2026. | F27: No verified company-level disbursement ledger obtained. | G27: S076, S077, S078, S001
A28: IN023 | B28: MBit Wireless | C28: 1 | D28: Yes — April 2026 roster | E28: DLI financial-support project approved in the 1 April 2026 roster. Cash disbursement not verified. No company-specific cash incentive verified. This is not evidence that none exists. EDA-tools access separately listed in April 2026. | F28: No verified company-level disbursement ledger obtained. | G28: S079, S080, S001
A29: IN024 | B29: Multi Nano Sense Technologies | C29: 1 | D29: Yes — April 2026 roster | E29: TDB INR 3.29 crore support in 2022, described by company as soft-loan support. New INR 37.51 crore RDI agreement announced 29 September 2026. DLI chip project also approved. Sanctions/agreements are not proof of full disbursement. EDA-tools access separately listed in April 2026. | F29: No verified company-level disbursement ledger obtained. | G29: S081, S082, S083, S084, S001
A30: IN025 | B30: Incise Infotech | C30: 1 | D30: Yes — April 2026 roster | E30: DLI financial-support project approved in the 1 April 2026 roster. Cash disbursement not verified. No company-specific cash incentive verified. This is not evidence that none exists. EDA-tools access separately listed in April 2026. | F30: No verified company-level disbursement ledger obtained. | G30: S085, S086, S087, S001
A31: IN026 | B31: WiSig Networks | C31: 1 | D31: Yes — April 2026 roster | E31: DLI financial support; DCIS grant of INR 5 crore reported for chip revision; C-DOT support. Avoid assigning the entire IIT Hyderabad research budget to WiSig. EDA-tools access separately listed in April 2026. | F31: No verified company-level disbursement ledger obtained. | G31: S088, S089, S090, S091, S001
A32: IN027 | B32: Aagyavision | C32: 1 | D32: Yes — April 2026 roster | E32: DLI financial support and IISc ecosystem support. AMD CSR grant is corporate, not a government subsidy. EDA-tools access separately listed in April 2026. | F32: No verified company-level disbursement ledger obtained. | G32: S092, S093, S094, S001
A33: IN028 | B33: Chipspirit Technologies | D33: Yes — April 2026 roster | E33: iDEX DISC1 winner in 2019; parliamentary SPARK support listing identifies INR 44.23 lakh. DLI EDA support, not verified DLI financial-project approval. | F33: No verified company-level disbursement ledger obtained. | G33: S095, S096, S097, S098, S001
A34: IN029 | B34: SandLogic Technologies | D34: Yes — April 2026 roster | E34: No company-specific cash incentive verified. This is not evidence that none exists. EDA-tools access separately listed in April 2026. | F34: No verified company-level disbursement ledger obtained. | G34: S099, S100, S101, S102, S001
A35: IN030 | B35: SimYog Technology | D35: Not established in April roster | E35: No company-specific cash incentive verified. This is not evidence that none exists. | F35: No verified company-level disbursement ledger obtained. | G35: S103, S104, S105, S106
A36: IN031 | B36: Ananant Systems | D36: Yes — April 2026 roster | E36: No company-specific cash incentive verified. This is not evidence that none exists. EDA-tools access separately listed in April 2026. | F36: No verified company-level disbursement ledger obtained. | G36: S107, S108, S109, S001
A37: IN032 | B37: VASBEAM | D37: Yes — April 2026 roster | E37: DLI EDA access and DCIS 2022–23 award reported. Programme-wide INR 50 crore pool is not the company grant amount. | F37: No verified company-level disbursement ledger obtained. | G37: S110, S111, S112, S001
A38: IN033 | B38: optoML | D38: Yes — April 2026 roster | E38: No company-specific cash incentive verified. This is not evidence that none exists. EDA-tools access separately listed in April 2026. | F38: No verified company-level disbursement ledger obtained. | G38: S113, S114, S115, S116, S117, S001
A39: IN034 | B39: CIMware Technologies | D39: Yes — April 2026 roster | E39: DLI EDA access; earlier DoT grants reported without fully reconciled amount. | F39: No verified company-level disbursement ledger obtained. | G39: S118, S119, S001
A40: IN035 | B40: Nanojoules Semiconductors | D40: Yes — April 2026 roster | E40: No company-specific cash incentive verified. This is not evidence that none exists. EDA-tools access separately listed in April 2026. | F40: No verified company-level disbursement ledger obtained. | G40: S120, S001
A41: IN036 | B41: Terminus Circuits | D41: Yes — April 2026 roster | E41: No company-specific cash incentive verified. This is not evidence that none exists. EDA-tools access separately listed in April 2026. | F41: No verified company-level disbursement ledger obtained. | G41: S121, S122, S001
A42: IN037 | B42: MemSmart | D42: Yes — April 2026 roster | E42: No company-specific cash incentive verified. This is not evidence that none exists. EDA-tools access separately listed in April 2026. | F42: No verified company-level disbursement ledger obtained. | G42: S123, S001
A43: IN038 | B43: Quanfluence | D43: Yes — April 2026 roster | E43: DLI EDA support. DoT development grants are reported; exact disbursed company amount not reconciled. | F43: No verified company-level disbursement ledger obtained. | G43: S124, S125, S126, S001
A44: IN039 | B44: TriSpace Technologies | D44: Yes — April 2026 roster | E44: No company-specific cash incentive verified. This is not evidence that none exists. EDA-tools access separately listed in April 2026. | F44: No verified company-level disbursement ledger obtained. | G44: S127, S128, S001
... A54: IN049 | B54: SiCSem | D54: Not established in April roster | E54: ISM project approval reported. Project cost and parent investment are not startup VC raised; disbursement not verified. | F54: No verified company-level disbursement ledger obtained. | G54: S155, S156, S157
A55: IN050 | B55: Saankhya Labs | C55: 1 | D55: Yes — April 2026 roster | E55: DLI financial-support project approved in the 1 April 2026 roster. Cash disbursement not verified. No company-specific cash incentive verified. This is not evidence that none exists. EDA-tools access separately listed in April 2026. | F55: No verified company-level disbursement ledger obtained. | G55: S158, S159, S001
A56: IN051 | B56: Meukron Technologies | D56: Not established in April roster | E56: IISc INCeNSE incubation; grant support reported without reconciled company cash amount. | F56: No verified company-level disbursement ledger obtained. | G56: S160, S161, S162
A57: IN052 | B57: LeadSOC Technologies | D57: Yes — April 2026 roster | E57: No company-specific cash incentive verified. This is not evidence that none exists. EDA-tools access separately listed in April 2026. | F57: No verified company-level disbursement ledger obtained. | G57: S163, S164, S001
A58: IN053 | B58: BITSILICA | D58: Yes — April 2026 roster | E58: No company-specific cash incentive verified. This is not evidence that none exists. EDA-tools access separately listed in April 2026. | F58: No verified company-level disbursement ledger obtained. | G58: S165, S166, S001
A59: IN054 | B59: IndieSemiC | D59: Yes — April 2026 roster | E59: DLI EDA roster; DST annual report identifies NIDHI-SSP support through GUSEC. Cash amount and disbursement not reconciled. | F59: No verified company-level disbursement ledger obtained. | G59: S167, S168, S169, S170, S171, S001
A60: IN055 | B60: Stteereng Silicon | D60: Yes — April 2026 roster | E60: Approved for EDA-tools access in 1 April 2026 parliamentary roster. No cash incentive established by this entry. | F60: No verified company-level disbursement ledger obtained. | G60: S001
A61: IN056 | B61: Silicon Support Solution (OPC) | D61: Yes — April 2026 roster | E61: Approved for EDA-tools access in 1 April 2026 parliamentary roster. No cash incentive established by this entry. | F61: No verified company-level disbursement ledger obtained. | G61: S001
A62: IN057 | B62: Tsilicon | D62: Yes — April 2026 roster | E62: Approved for EDA-tools access in 1 April 2026 parliamentary roster. No cash incentive established by this entry. | F62: No verified company-level disbursement ledger obtained. | G62: S001
A63: IN058 | B63: Semiksha Semiconductors | D63: Yes — April 2026 roster | E63: Approved for EDA-tools access in 1 April 2026 parliamentary roster. No cash incentive established by this entry. | F63: No verified company-level disbursement ledger obtained. | G63: S001
A64: IN059 | B64: iSOC Semiconductors | D64: Yes — April 2026 roster | E64: Approved for EDA-tools access in 1 April 2026 parliamentary roster. No cash incentive established by this entry. | F64: No verified company-level disbursement ledger obtained. | G64: S001
A65: IN060 | B65: PrimeSOC Technologies LLP | D65: Yes — April 2026 roster | E65: Approved for EDA-tools access in 1 April 2026 parliamentary roster. No cash incentive established by this entry. | F65: No verified company-level disbursement ledger obtained. | G65: S001
A66: IN061 | B66: Ciliconchip Circuit | D66: Yes — April 2026 roster | E66: Approved for EDA-tools access in 1 April 2026 parliamentary roster. No cash incentive established by this entry. | F66: No verified company-level disbursement ledger obtained. | G66: S001
A67: IN062 | B67: Memrym Solutions India | D67: Yes — April 2026 roster | E67: Approved for EDA-tools access in 1 April 2026 parliamentary roster. No cash incentive established by this entry. | F67: No verified company-level disbursement ledger obtained. | G67: S001
... A122: IN117 | B122: Aantaric Technologies | D122: Yes — April 2026 roster | E122: Approved for EDA-tools access in 1 April 2026 parliamentary roster. No cash incentive established by this entry. | F122: No verified company-level disbursement ledger obtained. | G122: S001
A123: IN118 | B123: MosChip Technologies | C123: 1 | D123: Not established in April roster | E123: DLI financial project approved. | F123: No verified company-level disbursement ledger obtained. | G123: S172, S001
A124: IN119 | B124: Elphins Technologies | D124: Not established in April roster | E124: Competition recognition is not treated as a cash grant. | F124: No verified company-level disbursement ledger obtained. | G124: S173
A125: IN120 | B125: CraftifAI Technologies | D125: Not established in April roster | E125: Competition recognition is not treated as a cash grant. | F125: No verified company-level disbursement ledger obtained. | G125: S174

Sheet DLI projects
A2: Official DLI financial-support projects
A3: 24 projects across 23 entities on 1 April 2026. Netrasemi has two. Project outlay is NOT sanctioned subsidy or cash received.
A5: Company | B5: Approved project description | C5: Project outlay (INR lakh) | D5: Source ID
A6: FermionIC Design | B6: 8–12 GHz hybrid-beamformer gain/phase chip | C6: 1047.19 | D6: S001
A7: Morphing Machines | B7: REDEFINE SoC, IP and accelerator card | C7: 2048.83 | D7: S001
A8: Calligo Technologies | B8: RISC-V / POSIT SoC and accelerator | C8: 4192.75 | D8: S001
A9: Sensesemi Technologies | B9: SenseSoC-200 IoT / medical SoC | C9: 3907.02 | D9: S001
A10: Saankhya Labs | B10: 5G baseband SoC | C10: 2558.77 | D10: S001
A11: Aryabhata Circuits and Research Labs | B11: Advanced tyre-monitoring IC | C11: 4095.49 | D11: S001
A12: BigEndian Semiconductors | B12: Video/audio surveillance SoC | C12: 3108 | D12: S001
A13: C2i Semiconductors | B13: Digital multiphase server-power controller | C13: 8375.2 | D13: S001
A14: MMRFIC Technology | B14: Ka-band radar beamformer | C14: 1253.04 | D14: S001
A15: Sophrosyne Technologies | B15: Low-power cardiac/vital-sign SoC | C15: 2147.1 | D15: S001
A16: Aagyavision | B16: Edge radar RF chips | C16: 2547.9 | D16: S001
A17: Aheesa Digital Innovations | B17: VEGA GPON / broadband network SoC | C17: 4140 | D17: S001
... A29: DV2JS Innovation / 3rdiTech | B29: Low-light single-photon image sensor | C29: 748 | D29: S001

Sheet Business model matrix
A2: Nine-part business-model matrix for every entry
A3: Filter by Company to see all nine requested fields. Revenue/cost descriptions are business-model inferences, not reported financial statements.
A5: ID | B5: Company | C5: Matrix component | D5: Company-specific business-model assessment | E5: Evidence status | F5: Supporting source IDs
A6: IN001 | B6: Mindgrove Technologies | C6: Value Proposition | D6: Inferred from stated offering: Local controllers for smart meters, access control, industrial devices and cameras can reduce dependence on imported controllers and improve local technical support. | E6: Analyst model; source facts separately identified. Not a company-approved canvas. | F6: S002, S003, S004, S005, S006, S001
A7: IN001 | B7: Mindgrove Technologies | C7: Customer Segment | D7: Device manufacturers, meter makers, camera and industrial-equipment designers. | E7: Analyst model; source facts separately identified. Not a company-approved canvas. | F7: S002, S003, S004, S005, S006, S001
A8: IN001 | B8: Mindgrove Technologies | C8: Customer Channel | D8: Inferred: direct technical sales, evaluation boards/samples and OEM design-in support. | E8: Analyst model; source facts separately identified. Not a company-approved canvas. | F8: S002, S003, S004, S005, S006, S001
A9: IN001 | B9: Mindgrove Technologies | C9: Customer Relationships | D9: Inferred: multi-year design-in relationship, qualification support, firmware/application engineering and lifecycle supply. | E9: Analyst model; source facts separately identified. Not a company-approved canvas. | F9: S002, S003, S004, S005, S006, S001
A10: IN001 | B10: Mindgrove Technologies | C10: Key Activities | D10: Inferred: architecture/design, verification, foundry coordination, silicon validation, qualification and application support. | E10: Analyst model; source facts separately identified. Not a company-approved canvas. | F10: S002, S003, S004, S005, S006, S001
A11: IN001 | B11: Mindgrove Technologies | C11: Key Resources | D11: Inferred: proprietary designs, engineering team, EDA access, test infrastructure and process know-how. Ownership must be verified. | E11: Analyst model; source facts separately identified. Not a company-approved canvas. | F11: S002, S003, S004, S005, S006, S001
A12: IN001 | B12: Mindgrove Technologies | C12: Key Partnerships | D12: Reported relationships: Bosch BGSW MoU / startup alliance; Pinetics integration. Neither establishes a guaranteed minimum purchase. PRAMA India agreement explores Vision SoC use in CCTV cameras; not a volume purchase commitment. | E12: Analyst model; source facts separately identified. Not a company-approved canvas. | F12: S002, S003, S004, S005, S006, S001
A13: IN001 | B13: Mindgrove Technologies | C13: Revenues | D13: Inferred: chip/module sales and possible paid custom development. Actual revenue, margins and pricing are not publicly verified. | E13: Analyst model; source facts separately identified. Not a company-approved canvas. | F13: S002, S003, S004, S005, S006, S001
A14: IN001 | B14: Mindgrove Technologies | C14: Costs | D14: Inferred: engineering payroll, EDA/IP licences, masks/tape-outs, wafers, packaging/test, qualification, applications support and inventory. | E14: Analyst model; source facts separately identified. Not a company-approved canvas. | F14: S002, S003, S004, S005, S006, S001
A15: IN002 | B15: Vervesemi Microelectronics | C15: Value Proposition | D15: Inferred from stated offering: More efficient fans and appliances, accurate smart meters, industrial motor drives and reliable aerospace instrumentation. | E15: Analyst model; source facts separately identified. Not a company-approved canvas. | F15: S007, S008, S009, S010, S001
A16: IN002 | B16: Vervesemi Microelectronics | C16: Customer Segment | D16: Industrial and appliance OEMs, meter manufacturers, space/defence electronics suppliers and chip designers licensing analog IP. | E16: Analyst model; source facts separately identified. Not a company-approved canvas. | F16: S007, S008, S009, S010, S001
... A1085: IN120 | B1085: CraftifAI Technologies | C1085: Costs | D1085: Unverified. The available roster/context does not establish this business-model field. | E1085: Unverified / diligence gap | F1085: S174

Sheet Indian beneficiary map
A2: Where large Indian companies could benefit
A3: Analyst mapping, except relationships explicitly described as confirmed. Startup products must pass customer and process qualification.
A5: Company / group | B5: Listing / ownership | C5: Position in value chain | D5: Potential benefit | E5: Relevant startup examples | F5: Important boundary | G5: Source / reference
A6: Tata Electronics / Tata Semiconductor Assembly | B6: Unlisted Tata businesses | C6: Silicon foundry and chip assembly/test | D6: Fabless logic/analog designs may create wafer and packaging demand after process/package qualification. | E6: Mindgrove, Vervesemi, Netrasemi, BigEndian, InCore-enabled customer designs | F6: Not a direct listed Tata-stock exposure. Node/IP compatibility and actual commissioning must be checked. | G6: https://www.tataelectronics.com/
A7: Kaynes Semicon / Kaynes Technology | B7: Subsidiary / listed parent | C7: OSAT and semiconductor backend | D7: Assembly, test and package engineering for Indian-designed chips. | E7: optoML and 3rdiTech consortium have named MoUs; other startups are prospective. | F7: MoUs are not guaranteed orders; qualify package, test programme, yield and price. | G7: https://www.kaynestechnology.co.in/
A8: CG Semi / CG Power | B8: JV / listed parent | C8: OSAT | D8: Potential domestic packaging/test provider and anchor ecosystem participant. | E8: Analog, power, RF and IoT chip startups, subject to qualification. | F8: Competes with other OSATs. Renesas/Stars relationship does not automatically extend to every startup. | G8: https://www.cgglobal.com/
A9: SiCSem / Archean Chemical Industries | B9: Corporate venture / listed parent | C9: SiC compound fab and packaging project | D9: Potential local SiC supply for EV and industrial power customers. | E9: Power-system OEMs and compatible SiC design/process partners. | F9: GaN is not SiC. Do not assume Agnit devices can be made in this process. | G9: https://sicsem.com/
A10: RIR Power Electronics | B10: Listed | C10: Power/compound-semiconductor ecosystem | D10: Potential process, packaging and market collaboration for power devices. | E10: Qualified power-device developers; relationship is hypothetical. | F10: Validate actual process capability and qualification; no startup contract assumed. | G10: https://www.ruttonsha.com/
A11: MosChip / Cyient / HCLTech | B11: Listed engineering/IP businesses | C11: Design services and integration | D11: Can license IP, use design tools, or integrate startup technology into customer ASICs. | E11: InCore, Maieutic, SimYog, Terminus; other design-service firms may also compete. | F11: HCL/Tessolve collaboration is stated by InCore; other named matches are analyst inference. | G11: https://incoresemi.com/news/incore-building-a-semiconductors-ecosystem-out-of-india/
A12: L&T Semiconductor Technologies | B12: Unlisted subsidiary of listed L&T | C12: Fabless products and design ecosystem | D12: Potential IP/tool user, technology partner or competitor. | E12: InCore, Maieutic, Terminus, analog and sensing startups. | F12: No purchase or acquisition intention assumed. | G12: https://www.ltsct.com/
A13: BEL / HAL / Data Patterns / Astra Microwave | B13: Listed | C13: Defence / aerospace equipment | D13: Could use qualified local RF, imaging, sensing and secure-compute chips. | E13: FermionIC, Agnit, MMRFIC, Aagyavision, 3rdiTech, Chipspirit. | F13: Long qualification and procurement cycles; end users may buy modules through tier-one integrators. | G13: https://bel-india.in/
A14: Dixon / Syrma SGS / Kaynes Technology | B14: Listed | C14: Electronics manufacturing and design | D14: Can integrate local chips when the brand owner approves the bill of materials. | E14: Mindgrove, Netrasemi, BigEndian, Sensesemi, HrdWyr. | F14: An EMS supplier may not control chip choice; qualify with both OEM and manufacturer. | G14: https://www.dixoninfo.com/
A15: Genus Power / HPL Electric | B15: Listed | C15: Smart metering | D15: Potential buyers of measurement, control and communications ICs. | E15: Vervesemi, Mindgrove, Sensesemi, WiSig, MBit. | F15: Meter certification, price and lifecycle supply are gating factors. | G15: https://genuspower.com/
A16: HFCL / Tejas Networks / ITI | B16: Listed | C16: Telecom equipment | D16: Potential customers for broadband, RF and wireless chips. | E16: Aheesa, Signalchip, WiSig, Ananant, Silizium, FermionIC. | F16: Interoperability and operator approval are essential; Tejas already owns Saankhya. | G16: https://www.tejasnetworks.com/
A17: Netweb Technologies | B17: Listed | C17: Servers / compute integration | D17: Potential integrator for qualified compute and power platforms. | E17: Calligo, optoML, Agrani, Morphing; C2i now an acquisition precedent. | F17: Performance-per-rupee and software compatibility determine adoption; no actual purchase assumed. | G17: https://netwebindia.com/

Sheet Sources
A2: Source register
A3: Publicly accessible company, investor, government and database pages reviewed on 1 October 2026. Source IDs accompany each company record.
A5: Source ID | B5: Company / scope | C5: Claims supported | D5: Publisher / document | E5: URL
A6: S001 | B6: All | C6: EDA roster / DLI project approval | D6: Government of India, Lok Sabha Q6140, 1 Apr 2026 | E6: https://sansad.in/getFile/loksabhaquestions/annex/187/AU6140_qbSWBV.pdf?source=pqals
A7: S002 | B7: Mindgrove Technologies | C7: Company, founders, funding, milestones | D7: www.mindgrovetech.in | E7: https://www.mindgrovetech.in/about-us
A8: S003 | B8: Mindgrove Technologies | C8: First silicon | D8: www.iitm.ac.in | E8: https://www.iitm.ac.in/happenings/press-releases-and-coverages/iit-m-start-mindgrove-technologies-launches-first
A9: S004 | B9: Mindgrove Technologies | C9: Bosch alliance | D9: www.bosch-softwaretechnologies.com | E9: https://www.bosch-softwaretechnologies.com/en/our-company/about-us/dna-nxt-start-up-alliance-program%E2%80%8B/success-stories/
A10: S005 | B10: Mindgrove Technologies | C10: Commercial progress, 17 Sep 2026 | D10: www.livemint.com | E10: https://www.livemint.com/companies/news/indian-chip-startup-mindgrove-technologies-eyes-first-revenues-this-fiscal-year-11789563796918.html
A11: S006 | B11: Mindgrove Technologies | C11: 15 August 2026 government milestone update | D11: www.pib.gov.in | E11: https://www.pib.gov.in/PressReleasePage.aspx?PRID=2299883&lang=1&reg=3
A12: S007 | B12: Vervesemi Microelectronics | C12: Founders / products | D12: www.vervesemi.com | E12: https://www.vervesemi.com/about.html
A13: S008 | B13: Vervesemi Microelectronics | C13: Funding, silicon status and government support | D13: www.pib.gov.in | E13: https://www.pib.gov.in/PressReleasePage.aspx?PRID=2229659&lang=1&reg=3
A14: S009 | B14: Vervesemi Microelectronics | C14: Samsung ecosystem and profile | D14: www.eoilisbon.gov.in | E14: https://www.eoilisbon.gov.in/docs/Startup-Profiles-%28120-companies%29-Bharat-Innovates-2026.pdf
A15: S010 | B15: Vervesemi Microelectronics | C15: 15 August 2026 government milestone update | D15: www.pib.gov.in | E15: https://www.pib.gov.in/PressReleasePage.aspx?PRID=2299883&lang=1&reg=3
A16: S011 | B16: FermionIC Design | C16: Founders / funding | D16: inc42.com | E16: https://inc42.com/company/fermionic-design/
... A179: S174 | B179: CraftifAI Technologies | C179: Discovery lead | D179: www.eetimes.com | E179: https://www.eetimes.com/semicon-india-2026-startup-mitra-sheds-light-on-early-stage-silicon-startup-funding/

Sheet Method and definitions
A2: Method, evidence rules and remaining gaps
A3: Read the company-level completeness notes before comparing totals or treating a company as investable.
A5: Topic | B5: Definition / treatment
A6: Coverage | B6: 120 entries, including 54 company-specific research profiles. The April 2026 official roster contributes all 103 EDA beneficiaries; remaining rows include detailed additional ventures, one DLI-listed incumbent and event leads. The universe is broad but cannot be certified as all operating Indian semiconductor startups.
A7: Research depth | B7: Company-specific profiles use multiple public sources where available. Roster-only entries have not been independently researched field by field; their unknown fields are deliberately unfilled and their matrices disclose gaps. They are discovery leads, not completed diligence.
A8: Scope | B8: Core focus is India-based/private semiconductor product, IP, design-tool, service, materials, equipment and packaging companies. Foreign-headquartered India-linked companies, mature firms, listed incumbents and acquired companies are retained with explicit boundaries. No DPIIT eligibility certification is implied.
A9: Date convention | B9: Research cutoff is 1 October 2026. The official EDA/DLI company list is dated 1 April 2026, not claimed current to October. Milestone target dates are not converted to completed events simply because time has passed.
A10: Database access | B10: Public Inc42 DataLabs, Crunchbase, CB Insights, Dealroom, Caplight and indexed Tracxn material were used where accessible. No authenticated PitchBook/Tracxn/Crunchbase paid export or private cap table was obtained. Search snippets are cross-checked against primary sources when possible.
A11: Funding totals | B11: Funding is not revenue, valuation, project cost or subsidy. Known event sums and database totals are explicitly distinguished. No sector-total funding number is calculated because disclosure coverage and instruments differ.
A12: Round counting | B12: A funding event/closing is not always a new financing round. C2i Series A and Maieutic seed extensions are included only incrementally. Agnit includes a historical angel event missing from some current databases.
A13: Conflicting values / averaging | B13: Do not average numbers from different dates, currency conversions, instruments or coverage scopes. That would create an unsupported total. Prefer original announcement/primary evidence, show material alternatives and retain a reconciliation note. Same-round rounding differences may be represented by the primary rounded figure.
A14: Currency | B14: Use USD Mn when a defensible source value exists. Original INR crore/lakh is retained for India-only funding and government project outlays. No invented FX rate is applied. One crore is 10 million rupees; one lakh is 100,000 rupees.
A15: Numeric blanks | B15: A blank funding/round cell means not verified or not disclosed, never zero or no funding. Text explains completeness. Where only a month/year is known, the date is stored at that precision and must not be interpreted as an exact day.
A16: DLI support | B16: Government answer describes up to 50% of eligible design expenditure, capped at INR 15 crore per application, and sales-linked incentive of 6% to 4% over five years, capped at INR 30 crore. Eligibility, milestones and sanction conditions apply. These caps are not amounts received by every company. Source S001.
... A25: Exhaustiveness limit | B25: The government roster includes companies outside an independent startup definition and excludes private ventures not using the scheme. There is no single authoritative public census containing founders, funding, subsidies, readiness and customers for every Indian semiconductor startup.
